<?xml version="1.0" ?>
<character id="19" name="Alisa">
	<moves>
		<move>
			<id>1</id>
			<name>in rage b+1+2</name>
			<command>in rage b+1+2</command>
			<hitLevel>h x 6, (DES)</hitLevel>
			<damage/>
			<StartUp>13</StartUp>
			<BlockFrame>-~+?</BlockFrame>
			<HitFrame>KND</HitFrame>
			<CounterHitFrame>KND</CounterHitFrame>
			<tags>
				<NeedsWork/>
				<RageArt/>
			</tags>
		</move>
		<move>
			<id>0</id>
			<name>1</name>
			<command>+1</command>
			<hitLevel>h</hitLevel>
			<damage>7</damage>
			<StartUp>10</StartUp>
			<BlockFrame>+1</BlockFrame>
			<HitFrame>+8</HitFrame>
			<CounterHitFrame>+8</CounterHitFrame>
			<tags>
				<NeedsWork/>
				<Safe/>
			</tags>
		</move>
		<move>
			<id>0</id>
			<name>1, 1</name>
			<command>+1, >, +1</command>
			<hitLevel>h, h</hitLevel>
			<damage>7,18</damage>
			<StartUp>10</StartUp>
			<BlockFrame>-3</BlockFrame>
			<HitFrame>+5</HitFrame>
			<CounterHitFrame>KND</CounterHitFrame>
			<tags>
				<NeedsWork/>
				<Safe/>
			</tags>
		</move>
		<move>
			<id>1</id>
			<name>1, 1, 1+2</name>
			<command>+1, >, +1, >, +1+2</command>
			<hitLevel>h, h, (DES)</hitLevel>
			<damage>7,18</damage>
			<StartUp>10</StartUp>
			<BlockFrame>-3?</BlockFrame>
			<HitFrame>+5?</HitFrame>
			<CounterHitFrame>KND</CounterHitFrame>
			<tags>
				<NeedsWork/>
			</tags>
		</move>
		<move>
			<id>2</id>
			<name>1, 2</name>
			<command>+1, >, +2</command>
			<hitLevel>h, h</hitLevel>
			<damage>7,10</damage>
			<StartUp>10</StartUp>
			<BlockFrame>-2</BlockFrame>
			<HitFrame>+4</HitFrame>
			<CounterHitFrame>+4?</CounterHitFrame>
			<tags>
				<NeedsWork/>
				<Safe/>
			</tags>
		</move>
		<move>
			<id>1</id>
			<name>1, 2, 2</name>
			<command>+1, >, +2, >, +2</command>
			<hitLevel>h, h, l</hitLevel>
			<damage>7,10,17</damage>
			<StartUp>10</StartUp>
			<BlockFrame>-11</BlockFrame>
			<HitFrame>+2</HitFrame>
			<CounterHitFrame>KND</CounterHitFrame>
			<tags>
				<NeedsWork/>
				<Punishable>-11</Punishable>
			</tags>
		</move>
		<move>
			<id>2</id>
			<name>1, 2, 2* (Very long hold)</name>
			<command>+1, >, +2, >, 2* (Very long hold)</command>
			<hitLevel>h, h, l</hitLevel>
			<damage>7,10,22</damage>
			<StartUp>10</StartUp>
			<BlockFrame>-10</BlockFrame>
			<HitFrame>KND</HitFrame>
			<CounterHitFrame>KND</CounterHitFrame>
			<tags>
				<NeedsWork/>
				<Punishable>-10</Punishable>
			</tags>
		</move>
		<move>
			<id>2</id>
			<name>1, 2, 4</name>
			<command>+1, >, +2, >, +4</command>
			<hitLevel>h, h, h</hitLevel>
			<damage>7,10,21</damage>
			<StartUp>10</StartUp>
			<BlockFrame>-5</BlockFrame>
			<HitFrame>KND</HitFrame>
			<CounterHitFrame>KND</CounterHitFrame>
			<tags>
				<NeedsWork/>
				<Safe/>
				<TailSpin/>
			</tags>
		</move>
		<move>
			<id>2</id>
			<name>2</name>
			<command>+2</command>
			<hitLevel>h</hitLevel>
			<damage>10</damage>
			<StartUp>12</StartUp>
			<BlockFrame>-6</BlockFrame>
			<HitFrame>+5</HitFrame>
			<CounterHitFrame>+5</CounterHitFrame>
			<tags>
				<NeedsWork/>
				<Safe/>
			</tags>
		</move>
		<move>
			<id>0</id>
			<name>2, 3</name>
			<command>+2, >, +3</command>
			<hitLevel>h, m</hitLevel>
			<damage>10,7</damage>
			<StartUp>12</StartUp>
			<BlockFrame>-10~-9</BlockFrame>
			<HitFrame>+2~+3</HitFrame>
			<CounterHitFrame>+2~+3</CounterHitFrame>
			<tags>
				<NeedsWork/>
			</tags>
		</move>
		<move>
			<id>1</id>
			<name>2, 3, 3</name>
			<command>+2, >, +3, >, +3</command>
			<hitLevel>h, m, m (TJ)</hitLevel>
			<damage>10,7,20</damage>
			<StartUp>12</StartUp>
			<BlockFrame>-11~-10</BlockFrame>
			<HitFrame>KND</HitFrame>
			<CounterHitFrame>KND</CounterHitFrame>
			<tags>
				<NeedsWork/>
				<TailSpin/>
			</tags>
		</move>
		<move>
			<id>2</id>
			<name>2, 3, 4</name>
			<command>+2, >, +3, >, +4</command>
			<hitLevel>h, m, l (TJ)</hitLevel>
			<damage>10,7,20</damage>
			<StartUp>12</StartUp>
			<BlockFrame>-19~-16</BlockFrame>
			<HitFrame>KND</HitFrame>
			<CounterHitFrame>KND</CounterHitFrame>
			<tags>
				<NeedsWork/>
			</tags>
		</move>
		<move>
			<id>2</id>
			<name>2, 4</name>
			<command>+2, >, +4</command>
			<hitLevel>h, h</hitLevel>
			<damage>10,21</damage>
			<StartUp>12</StartUp>
			<BlockFrame>-5?</BlockFrame>
			<HitFrame>KND</HitFrame>
			<CounterHitFrame>KND</CounterHitFrame>
			<tags>
				<NeedsWork/>
				<TailSpin/>
			</tags>
		</move>
		<move>
			<id>1</id>
			<name>3</name>
			<command>+3</command>
			<hitLevel>m</hitLevel>
			<damage>12</damage>
			<StartUp>14~15</StartUp>
			<BlockFrame>-12~-11</BlockFrame>
			<HitFrame>-1~0</HitFrame>
			<CounterHitFrame>-1~0</CounterHitFrame>
			<tags>
				<NeedsWork/>
			</tags>
		</move>
		<move>
			<id>0</id>
			<name>3, 2</name>
			<command>+3, >, +2</command>
			<hitLevel>m, m x 5, (DES)</hitLevel>
			<damage>12,4*5</damage>
			<StartUp>14~15</StartUp>
			<BlockFrame>-9</BlockFrame>
			<HitFrame>-1</HitFrame>
			<CounterHitFrame>-1</CounterHitFrame>
			<tags>
				<NeedsWork/>
				<Safe/>
			</tags>
		</move>
		<move>
			<id>1</id>
			<name>4</name>
			<command>+4</command>
			<hitLevel>h</hitLevel>
			<damage>24</damage>
			<StartUp>13</StartUp>
			<BlockFrame>-5</BlockFrame>
			<HitFrame>KND</HitFrame>
			<CounterHitFrame>KND</CounterHitFrame>
			<tags>
				<NeedsWork/>
				<Safe/>
				<TailSpin/>
				<Homing/>
			</tags>
		</move>
		<move>
			<id>0</id>
			<name>1+2</name>
			<command>+1+2</command>
			<hitLevel>m (TJ)</hitLevel>
			<damage>21</damage>
			<StartUp>33</StartUp>
			<BlockFrame>-5</BlockFrame>
			<HitFrame>KND</HitFrame>
			<CounterHitFrame>KND</CounterHitFrame>
			<tags>
				<NeedsWork/>
				<Safe/>
			</tags>
		</move>
		<move>
			<id>0</id>
			<name>f+2</name>
			<command>f+2</command>
			<hitLevel>m</hitLevel>
			<damage>12</damage>
			<StartUp>17</StartUp>
			<BlockFrame>-4</BlockFrame>
			<HitFrame>+7</HitFrame>
			<CounterHitFrame>+7</CounterHitFrame>
			<tags>
				<NeedsWork/>
				<Safe/>
			</tags>
		</move>
		<move>
			<id>0</id>
			<name>f+2, 1</name>
			<command>f+2, >, +1</command>
			<hitLevel>m, m, (DES)</hitLevel>
			<damage>12,20</damage>
			<StartUp>17</StartUp>
			<BlockFrame>-17~?</BlockFrame>
			<HitFrame>CS</HitFrame>
			<CounterHitFrame>CS</CounterHitFrame>
			<tags>
				<NeedsWork/>
			</tags>
		</move>
		<move>
			<id>1</id>
			<name>f+2, 1+2</name>
			<command>f+2, >, +1+2</command>
			<hitLevel>m, (DES)</hitLevel>
			<damage>12</damage>
			<StartUp>17</StartUp>
			<BlockFrame>-4</BlockFrame>
			<HitFrame>+7</HitFrame>
			<CounterHitFrame>+7</CounterHitFrame>
			<tags>
				<NeedsWork/>
				<Safe/>
			</tags>
		</move>
		<move>
			<id>1</id>
			<name>f+2, 3</name>
			<command>f+2, >, +3</command>
			<hitLevel>m, h (TJ)</hitLevel>
			<damage>12,8</damage>
			<StartUp>17</StartUp>
			<BlockFrame>-8</BlockFrame>
			<HitFrame>+4</HitFrame>
			<CounterHitFrame>+4</CounterHitFrame>
			<tags>
				<NeedsWork/>
				<Safe/>
			</tags>
		</move>
		<move>
			<id>1</id>
			<name>f+2, 3, f</name>
			<command>f+2, >, +3, >, f</command>
			<hitLevel>m, h (TJ), (Special)</hitLevel>
			<damage>12,8</damage>
			<StartUp>17</StartUp>
			<BlockFrame>-12</BlockFrame>
			<HitFrame>0</HitFrame>
			<CounterHitFrame>0</CounterHitFrame>
			<tags>
				<NeedsWork/>
				<Punishable>-12</Punishable>
			</tags>
		</move>
		<move>
			<id>2</id>
			<name>f+2, 3, 3</name>
			<command>f+2, >, +3, >, +3</command>
			<hitLevel>m, h (TJ), m</hitLevel>
			<damage>12,8,20</damage>
			<StartUp>17</StartUp>
			<BlockFrame>-10~-9</BlockFrame>
			<HitFrame>KND</HitFrame>
			<CounterHitFrame>KND</CounterHitFrame>
			<tags>
				<NeedsWork/>
			</tags>
		</move>
		<move>
			<id>2</id>
			<name>f+3</name>
			<command>f+3</command>
			<hitLevel>h</hitLevel>
			<damage>13</damage>
			<StartUp>14~15</StartUp>
			<BlockFrame>-14~-13</BlockFrame>
			<HitFrame>-3~-2</HitFrame>
			<CounterHitFrame>-3~-2</CounterHitFrame>
			<tags>
				<NeedsWork/>
			</tags>
		</move>
		<move>
			<id>0</id>
			<name>f+3, 2</name>
			<command>f+3, >, +2</command>
			<hitLevel>h, h, (DES)</hitLevel>
			<damage>13,20</damage>
			<StartUp>14~15</StartUp>
			<BlockFrame>-2?</BlockFrame>
			<HitFrame>SCD</HitFrame>
			<CounterHitFrame>SCD</CounterHitFrame>
			<tags>
				<NeedsWork/>
				<TailSpin/>
			</tags>
		</move>
		<move>
			<id>1</id>
			<name>f+3, 1+2</name>
			<command>f+3, >, +1+2</command>
			<hitLevel>h, m, (DES)</hitLevel>
			<damage>13,25</damage>
			<StartUp>14~15</StartUp>
			<BlockFrame>-13</BlockFrame>
			<HitFrame>CS</HitFrame>
			<CounterHitFrame>CS</CounterHitFrame>
			<tags>
				<NeedsWork/>
				<Punishable>-13</Punishable>
			</tags>
		</move>
		<move>
			<id>1</id>
			<name>f+4</name>
			<command>f+4</command>
			<hitLevel>m</hitLevel>
			<damage>14</damage>
			<StartUp>16</StartUp>
			<BlockFrame>-12</BlockFrame>
			<HitFrame>-2</HitFrame>
			<CounterHitFrame>-2</CounterHitFrame>
			<tags>
				<NeedsWork/>
				<Punishable>-12</Punishable>
				<Homing/>
			</tags>
		</move>
		<move>
			<id>0</id>
			<name>f+4, 1</name>
			<command>f+4, >, +1</command>
			<hitLevel>m, h</hitLevel>
			<damage>14,14</damage>
			<StartUp>16</StartUp>
			<BlockFrame>-9</BlockFrame>
			<HitFrame>KND</HitFrame>
			<CounterHitFrame>KND</CounterHitFrame>
			<tags>
				<NeedsWork/>
				<Safe/>
			</tags>
		</move>
		<move>
			<id>1</id>
			<name>f+4, 1, 4</name>
			<command>f+4, >, +1, >, +4</command>
			<hitLevel>m, h, m</hitLevel>
			<damage>14,14,24</damage>
			<StartUp>16</StartUp>
			<BlockFrame>-14~+11 (-12)</BlockFrame>
			<HitFrame>KND</HitFrame>
			<CounterHitFrame>KND</CounterHitFrame>
			<tags>
				<NeedsWork/>
			</tags>
		</move>
		<move>
			<id>2</id>
			<name>f+1+2</name>
			<command>f+1+2</command>
			<hitLevel>m</hitLevel>
			<damage>25</damage>
			<StartUp>14~16</StartUp>
			<BlockFrame>-12~-10</BlockFrame>
			<HitFrame>+7~+9</HitFrame>
			<CounterHitFrame>+7~+9</CounterHitFrame>
			<tags>
				<NeedsWork/>
			</tags>
		</move>
		<move>
			<id>0</id>
			<name>f+1+2, 3+4</name>
			<command>f+1+2, >, +3+4</command>
			<hitLevel>m, (Special) (TJ)(SBT)</hitLevel>
			<damage>25</damage>
			<StartUp>14~16a</StartUp>
			<BlockFrame>–</BlockFrame>
			<HitFrame>–</HitFrame>
			<CounterHitFrame>–</CounterHitFrame>
			<tags>
				<NeedsWork/>
			</tags>
		</move>
		<move>
			<id>1</id>
			<name>f+1+2, f+3+4</name>
			<command>f+1+2, >, f+3+4</command>
			<hitLevel>m, (Special) (TJ)(DBT)</hitLevel>
			<damage>25</damage>
			<StartUp>14~16a</StartUp>
			<BlockFrame>–</BlockFrame>
			<HitFrame>–</HitFrame>
			<CounterHitFrame>–</CounterHitFrame>
			<tags>
				<NeedsWork/>
			</tags>
		</move>
		<move>
			<id>1</id>
			<name>in rage f+2+3</name>
			<command>in rage f+2+3</command>
			<hitLevel>m (TJ)m</hitLevel>
			<damage>12,25</damage>
			<StartUp>16~17?</StartUp>
			<BlockFrame>-1?</BlockFrame>
			<HitFrame>SPD</HitFrame>
			<CounterHitFrame>SPD</CounterHitFrame>
			<tags>
				<NeedsWork/>
				<RageArt/>
			</tags>
		</move>
		<move>
			<id>0</id>
			<name>in rage f+2+3, 3+4</name>
			<command>in rage f+2+3, >, +3+4</command>
			<hitLevel>m (TJ)m, (SBT)</hitLevel>
			<damage>12,25</damage>
			<StartUp>16~17?</StartUp>
			<BlockFrame/>
			<HitFrame>SPD</HitFrame>
			<CounterHitFrame>SPD</CounterHitFrame>
			<tags>
				<NeedsWork/>
				<RageArt/>
			</tags>
		</move>
		<move>
			<id>1</id>
			<name>in rage f+2+3, f+3+4</name>
			<command>in rage f+2+3, >, f+3+4</command>
			<hitLevel>m (TJ)m, (DBT)</hitLevel>
			<damage>12,25</damage>
			<StartUp>16~17?</StartUp>
			<BlockFrame/>
			<HitFrame>SPD</HitFrame>
			<CounterHitFrame>SPD</CounterHitFrame>
			<tags>
				<NeedsWork/>
				<RageArt/>
			</tags>
		</move>
		<move>
			<id>1</id>
			<name>d/f+1</name>
			<command>d/f+1</command>
			<hitLevel>m</hitLevel>
			<damage>10</damage>
			<StartUp>13</StartUp>
			<BlockFrame>-6?</BlockFrame>
			<HitFrame>+5?</HitFrame>
			<CounterHitFrame>+8?</CounterHitFrame>
			<tags>
				<NeedsWork/>
			</tags>
		</move>
		<move>
			<id>0</id>
			<name>d/f+1, 1</name>
			<command>d/f+1, >, +1</command>
			<hitLevel>m, h</hitLevel>
			<damage>10,20</damage>
			<StartUp>13</StartUp>
			<BlockFrame>+1</BlockFrame>
			<HitFrame>+8</HitFrame>
			<CounterHitFrame>+8</CounterHitFrame>
			<tags>
				<NeedsWork/>
				<Safe/>
			</tags>
		</move>
		<move>
			<id>1</id>
			<name>d/f+1, 1, 2</name>
			<command>d/f+1, >, +1, >, +2</command>
			<hitLevel>m, h, h x 7, (DES)</hitLevel>
			<damage>10,20,4*7</damage>
			<StartUp>13</StartUp>
			<BlockFrame>+6</BlockFrame>
			<HitFrame>+8</HitFrame>
			<CounterHitFrame>+8</CounterHitFrame>
			<tags>
				<NeedsWork/>
				<Safe/>
			</tags>
		</move>
		<move>
			<id>2</id>
			<name>d/f+1, 4</name>
			<command>d/f+1, >, +4</command>
			<hitLevel>m, m</hitLevel>
			<damage>10,17</damage>
			<StartUp>13</StartUp>
			<BlockFrame>-9</BlockFrame>
			<HitFrame>+5 OC</HitFrame>
			<CounterHitFrame>KND</CounterHitFrame>
			<tags>
				<NeedsWork/>
				<Safe/>
			</tags>
		</move>
		<move>
			<id>1</id>
			<name>d/f+2</name>
			<command>d/f+2</command>
			<hitLevel>m</hitLevel>
			<damage>16</damage>
			<StartUp>16~17</StartUp>
			<BlockFrame>-9~-8</BlockFrame>
			<HitFrame>Launch (JG?)(+7)</HitFrame>
			<CounterHitFrame>Launch (JG?)</CounterHitFrame>
			<tags>
				<NeedsWork/>
			</tags>
		</move>
		<move>
			<id>0</id>
			<name>d/f+3</name>
			<command>d/f+3</command>
			<hitLevel>m</hitLevel>
			<damage>14</damage>
			<StartUp>16</StartUp>
			<BlockFrame>-12</BlockFrame>
			<HitFrame>-2</HitFrame>
			<CounterHitFrame>-2</CounterHitFrame>
			<tags>
				<NeedsWork/>
				<Punishable>-12</Punishable>
			</tags>
		</move>
		<move>
			<id>0</id>
			<name>d/f+3, 3</name>
			<command>d/f+3, >, +3</command>
			<hitLevel>m, l</hitLevel>
			<damage>14,17</damage>
			<StartUp>16</StartUp>
			<BlockFrame>-12</BlockFrame>
			<HitFrame>+1</HitFrame>
			<CounterHitFrame>KND</CounterHitFrame>
			<tags>
				<NeedsWork/>
				<Punishable>-12</Punishable>
			</tags>
		</move>
		<move>
			<id>1</id>
			<name>d/f+1+2</name>
			<command>d/f+1+2</command>
			<hitLevel>m, (DES)</hitLevel>
			<damage>25</damage>
			<StartUp>18</StartUp>
			<BlockFrame>-11?</BlockFrame>
			<HitFrame>CS</HitFrame>
			<CounterHitFrame>CS</CounterHitFrame>
			<tags>
				<NeedsWork/>
			</tags>
		</move>
		<move>
			<id>0</id>
			<name>d+2</name>
			<command>d+2</command>
			<hitLevel>m</hitLevel>
			<damage>17</damage>
			<StartUp>24~25</StartUp>
			<BlockFrame>-14~-13</BlockFrame>
			<HitFrame>+2~+3 OC</HitFrame>
			<CounterHitFrame>+2~+3 OC</CounterHitFrame>
			<tags>
				<NeedsWork/>
			</tags>
		</move>
		<move>
			<id>0</id>
			<name>d+2, 4</name>
			<command>d+2, >, +4</command>
			<hitLevel>m, m</hitLevel>
			<damage>17,24</damage>
			<StartUp>24~25( Air)</StartUp>
			<BlockFrame>-13~-11</BlockFrame>
			<HitFrame>KND</HitFrame>
			<CounterHitFrame>KND</CounterHitFrame>
			<tags>
				<NeedsWork/>
			</tags>
		</move>
		<move>
			<id>1</id>
			<name>d+2, 4, 1+2</name>
			<command>d+2, >, +4, >, +1+2</command>
			<hitLevel>m, m, (DES)</hitLevel>
			<damage>17,24</damage>
			<StartUp>24~25()( Air)</StartUp>
			<BlockFrame>-13~-11</BlockFrame>
			<HitFrame>KND</HitFrame>
			<CounterHitFrame>KND</CounterHitFrame>
			<tags>
				<NeedsWork/>
			</tags>
		</move>
		<move>
			<id>2</id>
			<name>d+3</name>
			<command>d+3</command>
			<hitLevel>l (TJ), (Special) (TC)</hitLevel>
			<damage>17</damage>
			<StartUp>23?s~</StartUp>
			<BlockFrame>-?~-?</BlockFrame>
			<HitFrame>+9~+13?</HitFrame>
			<CounterHitFrame>KND</CounterHitFrame>
			<tags>
				<NeedsWork/>
			</tags>
		</move>
		<move>
			<id>0</id>
			<name>d+3 (After stance ends)</name>
			<command>d+3 (After stance ends)</command>
			<hitLevel>l (TJ), (Special) (TC)</hitLevel>
			<damage>17</damage>
			<StartUp>23?s~</StartUp>
			<BlockFrame>-19?s~-?</BlockFrame>
			<HitFrame>-?</HitFrame>
			<CounterHitFrame>KND</CounterHitFrame>
			<tags>
				<NeedsWork/>
			</tags>
		</move>
		<move>
			<id>0</id>
			<name>d+4</name>
			<command>d+4</command>
			<hitLevel>l</hitLevel>
			<damage>15</damage>
			<StartUp>17</StartUp>
			<BlockFrame>-16</BlockFrame>
			<HitFrame>-5</HitFrame>
			<CounterHitFrame>-5</CounterHitFrame>
			<tags>
				<NeedsWork/>
				<Punishable>-16</Punishable>
			</tags>
		</move>
		<move>
			<id>0</id>
			<name>d+4, 1+2</name>
			<command>d+4, >, +1+2</command>
			<hitLevel>l, h</hitLevel>
			<damage>15,20</damage>
			<StartUp>17</StartUp>
			<BlockFrame>-1~0</BlockFrame>
			<HitFrame>KND</HitFrame>
			<CounterHitFrame>KND</CounterHitFrame>
			<tags>
				<NeedsWork/>
				<TailSpin/>
			</tags>
		</move>
		<move>
			<id>1</id>
			<name>d+3+4</name>
			<command>d+3+4</command>
			<hitLevel>l (TJ)</hitLevel>
			<damage>20</damage>
			<StartUp>27</StartUp>
			<BlockFrame>-18</BlockFrame>
			<HitFrame>KND</HitFrame>
			<CounterHitFrame>KND</CounterHitFrame>
			<tags>
				<NeedsWork/>
				<Punishable>-18</Punishable>
				<Homing/>
			</tags>
		</move>
		<move>
			<id>0</id>
			<name>d+3+4, 1+2</name>
			<command>d+3+4, >, +1+2</command>
			<hitLevel>l (TJ), (DES)</hitLevel>
			<damage>20</damage>
			<StartUp>27</StartUp>
			<BlockFrame>-18</BlockFrame>
			<HitFrame>KND</HitFrame>
			<CounterHitFrame>KND</CounterHitFrame>
			<tags>
				<NeedsWork/>
				<Punishable>-18</Punishable>
				<Homing/>
			</tags>
		</move>
		<move>
			<id>1</id>
			<name>d/b+2</name>
			<command>d/b+2</command>
			<hitLevel>m</hitLevel>
			<damage>17</damage>
			<StartUp>18</StartUp>
			<BlockFrame>-18</BlockFrame>
			<HitFrame>-5</HitFrame>
			<CounterHitFrame>-5</CounterHitFrame>
			<tags>
				<NeedsWork/>
				<Punishable>-18</Punishable>
			</tags>
		</move>
		<move>
			<id>0</id>
			<name>d/b+2, 2</name>
			<command>d/b+2, >, +2</command>
			<hitLevel>m, m</hitLevel>
			<damage>17,13</damage>
			<StartUp>18</StartUp>
			<BlockFrame>-10~-8</BlockFrame>
			<HitFrame>+14~+16 (SH)</HitFrame>
			<CounterHitFrame>+14~+16 (SH)</CounterHitFrame>
			<tags>
				<NeedsWork/>
			</tags>
		</move>
		<move>
			<id>1</id>
			<name>d/b+2, 2, 1+2</name>
			<command>d/b+2, >, +2, >, +1+2</command>
			<hitLevel>m, m, (DES)</hitLevel>
			<damage>17,13</damage>
			<StartUp>18</StartUp>
			<BlockFrame>-10~-8</BlockFrame>
			<HitFrame>+14~+16 (SH)</HitFrame>
			<CounterHitFrame>+14~+16 (SH)</CounterHitFrame>
			<tags>
				<NeedsWork/>
			</tags>
		</move>
		<move>
			<id>2</id>
			<name>d/b+3</name>
			<command>d/b+3</command>
			<hitLevel>l (TC)</hitLevel>
			<damage>11</damage>
			<StartUp>16 RC(cs4)</StartUp>
			<BlockFrame>-12?</BlockFrame>
			<HitFrame>-2?</HitFrame>
			<CounterHitFrame>+4?</CounterHitFrame>
			<tags>
				<NeedsWork/>
			</tags>
		</move>
		<move>
			<id>0</id>
			<name>d/b+4</name>
			<command>d/b+4</command>
			<hitLevel>l (TC)</hitLevel>
			<damage>23</damage>
			<StartUp>23~24 (cs6)</StartUp>
			<BlockFrame>-18~-17</BlockFrame>
			<HitFrame>KND</HitFrame>
			<CounterHitFrame>KND</CounterHitFrame>
			<tags>
				<NeedsWork/>
			</tags>
		</move>
		<move>
			<id>0</id>
			<name>b+1</name>
			<command>b+1</command>
			<hitLevel>m</hitLevel>
			<damage>15</damage>
			<StartUp>15~16 RC</StartUp>
			<BlockFrame>-5~-4</BlockFrame>
			<HitFrame>+8~+9</HitFrame>
			<CounterHitFrame>+8~+9</CounterHitFrame>
			<tags>
				<NeedsWork/>
			</tags>
		</move>
		<move>
			<id>0</id>
			<name>b+1, 1+2</name>
			<command>b+1, >, +1+2</command>
			<hitLevel>m, Sm, m</hitLevel>
			<damage>15,1,30</damage>
			<StartUp>15~16</StartUp>
			<BlockFrame>-16~-14</BlockFrame>
			<HitFrame>Launch</HitFrame>
			<CounterHitFrame>Launch</CounterHitFrame>
			<tags>
				<NeedsWork/>
			</tags>
		</move>
		<move>
			<id>1</id>
			<name>b+2</name>
			<command>b+2</command>
			<hitLevel>m</hitLevel>
			<damage>12</damage>
			<StartUp>18</StartUp>
			<BlockFrame>-12</BlockFrame>
			<HitFrame>-2</HitFrame>
			<CounterHitFrame>-2</CounterHitFrame>
			<tags>
				<NeedsWork/>
				<Punishable>-12</Punishable>
			</tags>
		</move>
		<move>
			<id>0</id>
			<name>b+2, 1</name>
			<command>b+2, >, +1</command>
			<hitLevel>m, m</hitLevel>
			<damage>12,17</damage>
			<StartUp>18</StartUp>
			<BlockFrame>-13~-12</BlockFrame>
			<HitFrame>0~+1 OC</HitFrame>
			<CounterHitFrame>KND</CounterHitFrame>
			<tags>
				<NeedsWork/>
			</tags>
		</move>
		<move>
			<id>1</id>
			<name>b+2, 4</name>
			<command>b+2, >, +4</command>
			<hitLevel>m, h</hitLevel>
			<damage>12,20</damage>
			<StartUp>18</StartUp>
			<BlockFrame>-9</BlockFrame>
			<HitFrame>KND</HitFrame>
			<CounterHitFrame>KND</CounterHitFrame>
			<tags>
				<NeedsWork/>
				<Safe/>
				<TailSpin/>
			</tags>
		</move>
		<move>
			<id>1</id>
			<name>b+3</name>
			<command>b+3</command>
			<hitLevel>m</hitLevel>
			<damage>26</damage>
			<StartUp>20~21</StartUp>
			<BlockFrame>-8~-7</BlockFrame>
			<HitFrame>KND</HitFrame>
			<CounterHitFrame>KND</CounterHitFrame>
			<tags>
				<NeedsWork/>
				<Homing/>
			</tags>
		</move>
		<move>
			<id>0</id>
			<name>b+4</name>
			<command>b+4</command>
			<hitLevel>m (TJ)</hitLevel>
			<damage>17</damage>
			<StartUp>15~16</StartUp>
			<BlockFrame>-12~-11</BlockFrame>
			<HitFrame>-3~-2</HitFrame>
			<CounterHitFrame>CS</CounterHitFrame>
			<tags>
				<NeedsWork/>
			</tags>
		</move>
		<move>
			<id>0</id>
			<name>b+4, 3</name>
			<command>b+4, >, +3</command>
			<hitLevel>m (TJ), m</hitLevel>
			<damage>17,15</damage>
			<StartUp>15~16</StartUp>
			<BlockFrame>-11</BlockFrame>
			<HitFrame>+6 OC</HitFrame>
			<CounterHitFrame>KND</CounterHitFrame>
			<tags>
				<NeedsWork/>
				<Punishable>-11</Punishable>
			</tags>
		</move>
		<move>
			<id>1</id>
			<name>b+4, 3, 1+2</name>
			<command>b+4, >, +3, >, +1+2</command>
			<hitLevel>m (TJ), m, (DES)</hitLevel>
			<damage>17,15</damage>
			<StartUp>15~16</StartUp>
			<BlockFrame>-11</BlockFrame>
			<HitFrame>+6 OC</HitFrame>
			<CounterHitFrame>KND</CounterHitFrame>
			<tags>
				<NeedsWork/>
				<Punishable>-11</Punishable>
			</tags>
		</move>
		<move>
			<id>2</id>
			<name>b+3+4</name>
			<command>b+3+4</command>
			<hitLevel>m (TJ)</hitLevel>
			<damage>20</damage>
			<StartUp>19~20</StartUp>
			<BlockFrame>-17~-16</BlockFrame>
			<HitFrame>Launch</HitFrame>
			<CounterHitFrame>Launch</CounterHitFrame>
			<tags>
				<NeedsWork/>
			</tags>
		</move>
		<move>
			<id>0</id>
			<name>b+3+4, 3+4</name>
			<command>b+3+4, >, +3+4</command>
			<hitLevel>m (TJ), m (TJ)</hitLevel>
			<damage>20,35</damage>
			<StartUp>19~20</StartUp>
			<BlockFrame>-3~+1 OC</BlockFrame>
			<HitFrame>KND</HitFrame>
			<CounterHitFrame>KND</CounterHitFrame>
			<tags>
				<NeedsWork/>
			</tags>
		</move>
		<move>
			<id>1</id>
			<name>b+2+3</name>
			<command>b+2+3</command>
			<hitLevel>!</hitLevel>
			<damage>50</damage>
			<StartUp>75</StartUp>
			<BlockFrame>KND</BlockFrame>
			<HitFrame>KND</HitFrame>
			<CounterHitFrame>KND</CounterHitFrame>
			<tags>
				<NeedsWork/>
			</tags>
		</move>
		<move>
			<id>0</id>
			<name>u/b+3+4</name>
			<command>u/b+3+4</command>
			<hitLevel>m (TJ)</hitLevel>
			<damage>25</damage>
			<StartUp>37~39</StartUp>
			<BlockFrame>+2~+4 OC</BlockFrame>
			<HitFrame>KND</HitFrame>
			<CounterHitFrame>KND</CounterHitFrame>
			<tags>
				<NeedsWork/>
			</tags>
		</move>
		<move>
			<id>0</id>
			<name>BT 3+4</name>
			<command>BT 3+4</command>
			<hitLevel>m (TJ)</hitLevel>
			<damage>25</damage>
			<StartUp>37~39 RBT</StartUp>
			<BlockFrame>+2~+4 OC</BlockFrame>
			<HitFrame>KND</HitFrame>
			<CounterHitFrame>KND</CounterHitFrame>
			<tags>
				<NeedsWork/>
			</tags>
		</move>
		<move>
			<id>0</id>
			<name>u/b+3+4, 1+2 or BT 3+4, 1+2</name>
			<command>u/b+3+4, >, 1+2 or BT 3+4, >, +1+2</command>
			<hitLevel>m (TJ), m</hitLevel>
			<damage>25,20</damage>
			<StartUp>37~39</StartUp>
			<BlockFrame>-20~-19</BlockFrame>
			<HitFrame>Launch</HitFrame>
			<CounterHitFrame>Launch</CounterHitFrame>
			<tags>
				<NeedsWork/>
			</tags>
		</move>
		<move>
			<id>2</id>
			<name>u/b or u or u/f+3</name>
			<command>u/b or u or u/f+3</command>
			<hitLevel>m (TJ)</hitLevel>
			<damage>15</damage>
			<StartUp>20( Air)</StartUp>
			<BlockFrame>-55</BlockFrame>
			<HitFrame>-29(SH)</HitFrame>
			<CounterHitFrame>-29(SH)</CounterHitFrame>
			<tags>
				<NeedsWork/>
				<Punishable>-55</Punishable>
			</tags>
		</move>
		<move>
			<id>0</id>
			<name>u/f+3, 2</name>
			<command>u/f+3, >, +2</command>
			<hitLevel>m (TJ), m (TJ)</hitLevel>
			<damage>15,30</damage>
			<StartUp>20()</StartUp>
			<BlockFrame>-14~-12</BlockFrame>
			<HitFrame>KND</HitFrame>
			<CounterHitFrame>KND</CounterHitFrame>
			<tags>
				<NeedsWork/>
			</tags>
		</move>
		<move>
			<id>1</id>
			<name>u/f+3, 3+4</name>
			<command>u/f+3, >, +3+4</command>
			<hitLevel>m (TJ), (Special) (TJ)(SBT)</hitLevel>
			<damage>15</damage>
			<StartUp>20() Air</StartUp>
			<BlockFrame>-29</BlockFrame>
			<HitFrame>-3(SH)</HitFrame>
			<CounterHitFrame>-3(SH)</CounterHitFrame>
			<tags>
				<NeedsWork/>
				<Punishable>-29</Punishable>
			</tags>
		</move>
		<move>
			<id>1</id>
			<name>u/f+3, f+3+4</name>
			<command>u/f+3, >, f+3+4</command>
			<hitLevel>m (TJ), (Special) (TJ)(DBT)</hitLevel>
			<damage>15</damage>
			<StartUp>20() Air</StartUp>
			<BlockFrame>-29</BlockFrame>
			<HitFrame>-3(SH)</HitFrame>
			<CounterHitFrame>-3(SH)</CounterHitFrame>
			<tags>
				<NeedsWork/>
				<Punishable>-29</Punishable>
			</tags>
		</move>
		<move>
			<id>1</id>
			<name>u or u/f+4</name>
			<command>u or u/f+4</command>
			<hitLevel>m (TJ)</hitLevel>
			<damage>10</damage>
			<StartUp>15~16</StartUp>
			<BlockFrame>-15~-14?</BlockFrame>
			<HitFrame>+</HitFrame>
			<CounterHitFrame>+</CounterHitFrame>
			<tags>
				<NeedsWork/>
			</tags>
		</move>
		<move>
			<id>0</id>
			<name>u/f+4, 4</name>
			<command>u/f+4, >, +4</command>
			<hitLevel>m (TJ), m</hitLevel>
			<damage>10,10</damage>
			<StartUp>15~16</StartUp>
			<BlockFrame>-13~-12s</BlockFrame>
			<HitFrame>BU</HitFrame>
			<CounterHitFrame>BU</CounterHitFrame>
			<tags>
				<NeedsWork/>
			</tags>
		</move>
		<move>
			<id>1</id>
			<name>u or u/f+3+4</name>
			<command>u or u/f+3+4</command>
			<hitLevel>m (TJ)</hitLevel>
			<damage>28</damage>
			<StartUp>38~39</StartUp>
			<BlockFrame>0~+1 OC</BlockFrame>
			<HitFrame>KND</HitFrame>
			<CounterHitFrame>KND</CounterHitFrame>
			<tags>
				<NeedsWork/>
			</tags>
		</move>
		<move>
			<id>0</id>
			<name>f, F+2</name>
			<command>f, >, F+2</command>
			<hitLevel>m (TJ)</hitLevel>
			<damage>18</damage>
			<StartUp>16~17 (17~)</StartUp>
			<BlockFrame>-18~-17</BlockFrame>
			<HitFrame>KND</HitFrame>
			<CounterHitFrame>KND</CounterHitFrame>
			<tags>
				<NeedsWork/>
			</tags>
		</move>
		<move>
			<id>1</id>
			<name>f, F+2, 3</name>
			<command>f, >, F+2, >, +3</command>
			<hitLevel>m (TJ), m</hitLevel>
			<damage>18,25</damage>
			<StartUp>16~17 (17~)</StartUp>
			<BlockFrame>-13</BlockFrame>
			<HitFrame>KND</HitFrame>
			<CounterHitFrame>KND</CounterHitFrame>
			<tags>
				<NeedsWork/>
				<Punishable>-13</Punishable>
			</tags>
		</move>
		<move>
			<id>2</id>
			<name>f, F+3</name>
			<command>f, >, F+3</command>
			<hitLevel>m</hitLevel>
			<damage>12</damage>
			<StartUp>18~19 (19~)</StartUp>
			<BlockFrame>-18~-17</BlockFrame>
			<HitFrame>-6~-5</HitFrame>
			<CounterHitFrame>-6~-5</CounterHitFrame>
			<tags>
				<NeedsWork/>
			</tags>
		</move>
		<move>
			<id>1</id>
			<name>f, F+3, 4</name>
			<command>f, >, F+3, >, +4</command>
			<hitLevel>m, h (TJ)</hitLevel>
			<damage>12,15</damage>
			<StartUp>18~19 (19~)</StartUp>
			<BlockFrame>-9</BlockFrame>
			<HitFrame>KND</HitFrame>
			<CounterHitFrame>KND</CounterHitFrame>
			<tags>
				<NeedsWork/>
				<Safe/>
			</tags>
		</move>
		<move>
			<id>2</id>
			<name>f, F+3, 4, 1+2</name>
			<command>f, >, F+3, >, +4, >, +1+2</command>
			<hitLevel>m, h (TJ), (DES)</hitLevel>
			<damage>12,15</damage>
			<StartUp>18~19 (19~)</StartUp>
			<BlockFrame>-9</BlockFrame>
			<HitFrame>KND</HitFrame>
			<CounterHitFrame>KND</CounterHitFrame>
			<tags>
				<NeedsWork/>
				<Safe/>
			</tags>
		</move>
		<move>
			<id>3</id>
			<name>f, F+3, 4, 4</name>
			<command>f, >, F+3, >, +4, >, +4</command>
			<hitLevel>m, h (TJ), m</hitLevel>
			<damage>12,15,25</damage>
			<StartUp>18~19 (19~)</StartUp>
			<BlockFrame>-10</BlockFrame>
			<HitFrame>KND</HitFrame>
			<CounterHitFrame>KND</CounterHitFrame>
			<tags>
				<NeedsWork/>
				<Punishable>-10</Punishable>
				<TailSpin/>
			</tags>
		</move>
		<move>
			<id>3</id>
			<name>f, F+3, 4, 4, 1+2</name>
			<command>f, >, F+3, >, +4, >, +4, >, +1+2</command>
			<hitLevel>m, h (TJ), m, (DES)</hitLevel>
			<damage>12,15,25</damage>
			<StartUp>18~19 (19~)</StartUp>
			<BlockFrame>-10</BlockFrame>
			<HitFrame>KND</HitFrame>
			<CounterHitFrame>KND</CounterHitFrame>
			<tags>
				<NeedsWork/>
				<Punishable>-10</Punishable>
				<TailSpin/>
			</tags>
		</move>
		<move>
			<id>4</id>
			<name>f, F+4</name>
			<command>f, >, F+4</command>
			<hitLevel>m</hitLevel>
			<damage>18</damage>
			<StartUp>19~22 (20~)</StartUp>
			<BlockFrame>-11~-8</BlockFrame>
			<HitFrame>Throw(+5OB)</HitFrame>
			<CounterHitFrame>Throw(+5OB)</CounterHitFrame>
			<tags>
				<NeedsWork/>
			</tags>
		</move>
		<move>
			<id>1</id>
			<name>f, F+4 When hit f or b+1</name>
			<command>f, >, F+4 When hit f or b+1</command>
			<hitLevel>m, m</hitLevel>
			<damage>18,22</damage>
			<StartUp>19(20~)</StartUp>
			<BlockFrame/>
			<HitFrame>KND</HitFrame>
			<CounterHitFrame/>
			<tags>
				<NeedsWork/>
			</tags>
		</move>
		<move>
			<id>1</id>
			<name>f, F+1+2</name>
			<command>f, >, F+1+2</command>
			<hitLevel>mm</hitLevel>
			<damage>5,18</damage>
			<StartUp>17,30 (18~)</StartUp>
			<BlockFrame>-16</BlockFrame>
			<HitFrame>CS</HitFrame>
			<CounterHitFrame>CS</CounterHitFrame>
			<tags>
				<NeedsWork/>
				<Punishable>-16</Punishable>
			</tags>
		</move>
		<move>
			<id>1</id>
			<name>f, F+1+2 When hit 2</name>
			<command>f, >, F+1+2 When hit 2</command>
			<hitLevel>mm, m x 6, (DES)</hitLevel>
			<damage>5,18,2*6</damage>
			<StartUp>17,30 (18~)</StartUp>
			<BlockFrame/>
			<HitFrame>CS</HitFrame>
			<CounterHitFrame>CS</CounterHitFrame>
			<tags>
				<NeedsWork/>
			</tags>
		</move>
		<move>
			<id>1</id>
			<name>b, f+2</name>
			<command>b, >, f+2</command>
			<hitLevel>h</hitLevel>
			<damage>26</damage>
			<StartUp>16~24 (16~)</StartUp>
			<BlockFrame>-8~0</BlockFrame>
			<HitFrame>KND</HitFrame>
			<CounterHitFrame>KND</CounterHitFrame>
			<tags>
				<NeedsWork/>
				<PowerCrush/>
			</tags>
		</move>
		<move>
			<id>1</id>
			<name>b, B+1+4</name>
			<command>b, >, B+1+4</command>
			<hitLevel>h! (TJ)</hitLevel>
			<damage>50</damage>
			<StartUp>63~80 (64~)</StartUp>
			<BlockFrame>KND</BlockFrame>
			<HitFrame>KND</HitFrame>
			<CounterHitFrame>KND</CounterHitFrame>
			<tags>
				<NeedsWork/>
			</tags>
		</move>
		<move>
			<id>1</id>
			<name>f, f, f+2</name>
			<command>f, >, f, >, f+2</command>
			<hitLevel>h</hitLevel>
			<damage>30</damage>
			<StartUp>13(16~)</StartUp>
			<BlockFrame>+4</BlockFrame>
			<HitFrame>ATD</HitFrame>
			<CounterHitFrame>ATD</CounterHitFrame>
			<tags>
				<NeedsWork/>
				<Safe/>
			</tags>
		</move>
		<move>
			<id>2</id>
			<name>f, f, f+3</name>
			<command>f, >, f, >, f+3</command>
			<hitLevel>m (TJ)</hitLevel>
			<damage>15</damage>
			<StartUp>18(21~)</StartUp>
			<BlockFrame>-4</BlockFrame>
			<HitFrame>+6</HitFrame>
			<CounterHitFrame>+6</CounterHitFrame>
			<tags>
				<NeedsWork/>
				<Safe/>
			</tags>
		</move>
		<move>
			<id>2</id>
			<name>f, f, f+3, 4</name>
			<command>f, >, f, >, f+3, >, +4</command>
			<hitLevel>m (TJ), m (TJ)</hitLevel>
			<damage>15,20</damage>
			<StartUp>18(21~)</StartUp>
			<BlockFrame>-7</BlockFrame>
			<HitFrame>KND</HitFrame>
			<CounterHitFrame>KND</CounterHitFrame>
			<tags>
				<NeedsWork/>
				<Safe/>
				<TailSpin/>
			</tags>
		</move>
		<move>
			<id>3</id>
			<name>2+4+1+2</name>
			<command>2+4+1+2</command>
			<hitLevel>m (TJ)</hitLevel>
			<damage>24</damage>
			<StartUp>18</StartUp>
			<BlockFrame>-3</BlockFrame>
			<HitFrame>KND</HitFrame>
			<CounterHitFrame>KND</CounterHitFrame>
			<tags>
				<NeedsWork/>
				<Safe/>
			</tags>
		</move>
		<move>
			<id>0</id>
			<name>WS+1</name>
			<command>WS+1</command>
			<hitLevel>m</hitLevel>
			<damage>12</damage>
			<StartUp>13</StartUp>
			<BlockFrame>-12</BlockFrame>
			<HitFrame>-1</HitFrame>
			<CounterHitFrame>-1</CounterHitFrame>
			<tags>
				<NeedsWork/>
				<Punishable>-12</Punishable>
			</tags>
		</move>
		<move>
			<id>0</id>
			<name>WS+1, 2</name>
			<command>WS+1, >, +2</command>
			<hitLevel>m, h</hitLevel>
			<damage>12,9</damage>
			<StartUp>13</StartUp>
			<BlockFrame>-5</BlockFrame>
			<HitFrame>+6</HitFrame>
			<CounterHitFrame>+6</CounterHitFrame>
			<tags>
				<NeedsWork/>
				<Safe/>
			</tags>
		</move>
		<move>
			<id>1</id>
			<name>WS+1, 2, 3</name>
			<command>WS+1, >, +2, >, +3</command>
			<hitLevel>m, h, m</hitLevel>
			<damage>12,9,23</damage>
			<StartUp>13</StartUp>
			<BlockFrame>-10</BlockFrame>
			<HitFrame>Launch</HitFrame>
			<CounterHitFrame>Launch</CounterHitFrame>
			<tags>
				<NeedsWork/>
				<Punishable>-10</Punishable>
			</tags>
		</move>
		<move>
			<id>2</id>
			<name>WS+1, 2, 3, 1+2</name>
			<command>WS+1, >, +2, >, +3, >, +1+2</command>
			<hitLevel>m, h, m, (DES)</hitLevel>
			<damage>12,9,23</damage>
			<StartUp>13</StartUp>
			<BlockFrame>-10</BlockFrame>
			<HitFrame>Launch</HitFrame>
			<CounterHitFrame>Launch</CounterHitFrame>
			<tags>
				<NeedsWork/>
				<Punishable>-10</Punishable>
			</tags>
		</move>
		<move>
			<id>3</id>
			<name>WS+2</name>
			<command>WS+2</command>
			<hitLevel>m</hitLevel>
			<damage>24</damage>
			<StartUp>17~18</StartUp>
			<BlockFrame>-13~-12</BlockFrame>
			<HitFrame>Launch</HitFrame>
			<CounterHitFrame>Launch</CounterHitFrame>
			<tags>
				<NeedsWork/>
			</tags>
		</move>
		<move>
			<id>0</id>
			<name>WS+2, 3+4</name>
			<command>WS+2, >, +3+4</command>
			<hitLevel>m, (Special) (TJ)(SBT)</hitLevel>
			<damage>24</damage>
			<StartUp>17~18 Air</StartUp>
			<BlockFrame>-6~-5</BlockFrame>
			<HitFrame>Launch</HitFrame>
			<CounterHitFrame>Launch</CounterHitFrame>
			<tags>
				<NeedsWork/>
			</tags>
		</move>
		<move>
			<id>1</id>
			<name>WS+2, f+3+4</name>
			<command>WS+2, >, f+3+4</command>
			<hitLevel>m, (Special) (TJ)(DBT)</hitLevel>
			<damage>24</damage>
			<StartUp>17~18 Air</StartUp>
			<BlockFrame>-6~-5</BlockFrame>
			<HitFrame>Launch</HitFrame>
			<CounterHitFrame>Launch</CounterHitFrame>
			<tags>
				<NeedsWork/>
			</tags>
		</move>
		<move>
			<id>1</id>
			<name>WS+3</name>
			<command>WS+3</command>
			<hitLevel>m, (Special)</hitLevel>
			<damage>18</damage>
			<StartUp>19 Air</StartUp>
			<BlockFrame>-137</BlockFrame>
			<HitFrame>-124</HitFrame>
			<CounterHitFrame>-124</CounterHitFrame>
			<tags>
				<NeedsWork/>
				<Punishable>-137</Punishable>
			</tags>
		</move>
		<move>
			<id>0</id>
			<name>WS+3, 3, B (Cancel)</name>
			<command>WS+3, >, +3, >, B (Cancel)</command>
			<hitLevel>m, (Special)</hitLevel>
			<damage>18</damage>
			<StartUp>19</StartUp>
			<BlockFrame>-14</BlockFrame>
			<HitFrame>-1</HitFrame>
			<CounterHitFrame>-1</CounterHitFrame>
			<tags>
				<NeedsWork/>
				<Punishable>-14</Punishable>
			</tags>
		</move>
		<move>
			<id>2</id>
			<name>WS+3, 3 (one spin)</name>
			<command>WS+3, >, 3 (one spin)</command>
			<hitLevel>m</hitLevel>
			<damage>20</damage>
			<StartUp>19</StartUp>
			<BlockFrame>-10</BlockFrame>
			<HitFrame>+k</HitFrame>
			<CounterHitFrame>SCD</CounterHitFrame>
			<tags>
				<NeedsWork/>
				<Punishable>-10</Punishable>
				<TailSpin/>
			</tags>
		</move>
		<move>
			<id>1</id>
			<name>WS+3, 3 (two spins)</name>
			<command>WS+3, >, 3 (two spins)</command>
			<hitLevel>m</hitLevel>
			<damage>22</damage>
			<StartUp>19</StartUp>
			<BlockFrame>-10</BlockFrame>
			<HitFrame>SCD</HitFrame>
			<CounterHitFrame>SCD</CounterHitFrame>
			<tags>
				<NeedsWork/>
				<Punishable>-10</Punishable>
				<TailSpin/>
			</tags>
		</move>
		<move>
			<id>1</id>
			<name>WS+3, 3</name>
			<command>WS+3, >, +3</command>
			<hitLevel>m</hitLevel>
			<damage>22</damage>
			<StartUp>19</StartUp>
			<BlockFrame>-4</BlockFrame>
			<HitFrame>SCD</HitFrame>
			<CounterHitFrame>SCD</CounterHitFrame>
			<tags>
				<NeedsWork/>
				<Safe/>
				<TailSpin/>
			</tags>
		</move>
		<move>
			<id>1</id>
			<name>WS+3, d+3</name>
			<command>WS+3, >, d+3</command>
			<hitLevel>l (TC)</hitLevel>
			<damage>20</damage>
			<StartUp>19 RC</StartUp>
			<BlockFrame>-12</BlockFrame>
			<HitFrame>KND</HitFrame>
			<CounterHitFrame>KND</CounterHitFrame>
			<tags>
				<NeedsWork/>
				<Punishable>-12</Punishable>
			</tags>
		</move>
		<move>
			<id>1</id>
			<name>WS+1+2</name>
			<command>WS+1+2</command>
			<hitLevel>m</hitLevel>
			<damage>20</damage>
			<StartUp>20 RC</StartUp>
			<BlockFrame>-8</BlockFrame>
			<HitFrame>KND</HitFrame>
			<CounterHitFrame>KND</CounterHitFrame>
			<tags>
				<NeedsWork/>
				<Safe/>
				<Homing/>
			</tags>
		</move>
		<move>
			<id>0</id>
			<name>WS+1+2, * (two spins)</name>
			<command>WS+1+2, >, * (two spins)</command>
			<hitLevel>m</hitLevel>
			<damage>24</damage>
			<StartUp>28 RC</StartUp>
			<BlockFrame>-4</BlockFrame>
			<HitFrame>KND</HitFrame>
			<CounterHitFrame>KND</CounterHitFrame>
			<tags>
				<NeedsWork/>
				<Safe/>
				<Homing/>
			</tags>
		</move>
		<move>
			<id>1</id>
			<name>WS+1+2, * (three spins)</name>
			<command>WS+1+2, >, * (three spins)</command>
			<hitLevel>m</hitLevel>
			<damage>28</damage>
			<StartUp>39 RC</StartUp>
			<BlockFrame>0</BlockFrame>
			<HitFrame>KND</HitFrame>
			<CounterHitFrame>KND</CounterHitFrame>
			<tags>
				<NeedsWork/>
				<Safe/>
				<Homing/>
			</tags>
		</move>
		<move>
			<id>1</id>
			<name>FC+d/f+1+2</name>
			<command>FC+d/f+1+2</command>
			<hitLevel>ll</hitLevel>
			<damage>10,16</damage>
			<StartUp>23,33~34</StartUp>
			<BlockFrame>-11~-10</BlockFrame>
			<HitFrame>+4~+5?s</HitFrame>
			<CounterHitFrame>+4~+5?s</CounterHitFrame>
			<tags>
				<NeedsWork/>
			</tags>
		</move>
		<move>
			<id>0</id>
			<name>FC+d/f+1+2 , 1+2</name>
			<command>FC+d/f+1+2, >, +1+2</command>
			<hitLevel>ll, (DES)</hitLevel>
			<damage>10,16</damage>
			<StartUp>23,33~34</StartUp>
			<BlockFrame>-11~-10</BlockFrame>
			<HitFrame>+5~+6 OC</HitFrame>
			<CounterHitFrame>+5~+6 OC</CounterHitFrame>
			<tags>
				<NeedsWork/>
			</tags>
		</move>
		<move>
			<id>1</id>
			<name>SS+4</name>
			<command>SS+4</command>
			<hitLevel>l</hitLevel>
			<damage>15</damage>
			<StartUp>24(33~)</StartUp>
			<BlockFrame>-12</BlockFrame>
			<HitFrame>-1</HitFrame>
			<CounterHitFrame>+7</CounterHitFrame>
			<tags>
				<NeedsWork/>
				<Punishable>-12</Punishable>
			</tags>
		</move>
		<move>
			<id>0</id>
			<name>SS+4 , 1+2</name>
			<command>SS+4, >, +1+2</command>
			<hitLevel>l, h x 3 (TJ), m (TJ)</hitLevel>
			<damage>15,5*4</damage>
			<StartUp>24(33~)</StartUp>
			<BlockFrame>-10</BlockFrame>
			<HitFrame>+1</HitFrame>
			<CounterHitFrame>+1</CounterHitFrame>
			<tags>
				<NeedsWork/>
				<Punishable>-10</Punishable>
			</tags>
		</move>
		<move>
			<id>1</id>
			<name>BT 4</name>
			<command>BT 4</command>
			<hitLevel>m (TJ)</hitLevel>
			<damage>20</damage>
			<StartUp>16~17 RBT</StartUp>
			<BlockFrame>-3~-2</BlockFrame>
			<HitFrame>KND</HitFrame>
			<CounterHitFrame>KND</CounterHitFrame>
			<tags>
				<NeedsWork/>
			</tags>
		</move>
		<move>
			<id>0</id>
			<name>Opponent Down d/b+1+2</name>
			<command>Opponent Down d/b+1+2</command>
			<hitLevel>l?(On grounded opponent)</hitLevel>
			<damage/>
			<StartUp>16~17</StartUp>
			<BlockFrame>–</BlockFrame>
			<HitFrame/>
			<CounterHitFrame/>
			<tags>
				<NeedsWork/>
			</tags>
		</move>
		<move>
			<id>0</id>
			<name>Grounded face up 1+2</name>
			<command>Grounded face up 1+2</command>
			<hitLevel>(Special) (TJ)</hitLevel>
			<damage/>
			<StartUp>Air</StartUp>
			<BlockFrame/>
			<HitFrame/>
			<CounterHitFrame/>
			<tags>
				<NeedsWork/>
			</tags>
		</move>
		<move>
			<id>0</id>
			<name>Grounded face up 1+2, 3+4</name>
			<command>Grounded face up 1+2, >, +3+4</command>
			<hitLevel>(Special) (TJ), m (TJ)</hitLevel>
			<damage>35</damage>
			<StartUp>42</StartUp>
			<BlockFrame>-10</BlockFrame>
			<HitFrame>KND</HitFrame>
			<CounterHitFrame>KND</CounterHitFrame>
			<tags>
				<NeedsWork/>
				<Punishable>-10</Punishable>
			</tags>
		</move>
		<move>
			<id>1</id>
			<name>1+2+3</name>
			<command>1+2+3</command>
			<hitLevel>(Special) (TJ)</hitLevel>
			<damage/>
			<StartUp>Air</StartUp>
			<BlockFrame/>
			<HitFrame/>
			<CounterHitFrame/>
			<tags>
				<NeedsWork/>
			</tags>
		</move>
		<move>
			<id>0</id>
			<name>1+2+4</name>
			<command>1+2+4</command>
			<hitLevel>(Special)</hitLevel>
			<damage/>
			<StartUp>()</StartUp>
			<BlockFrame/>
			<HitFrame/>
			<CounterHitFrame/>
			<tags>
				<NeedsWork/>
			</tags>
		</move>
		<move>
			<id>0</id>
			<name>1+2+3+4</name>
			<command>1+2+3+4</command>
			<hitLevel>(Special) (TJ)</hitLevel>
			<damage/>
			<StartUp>Air</StartUp>
			<BlockFrame/>
			<HitFrame/>
			<CounterHitFrame/>
			<tags>
				<NeedsWork/>
			</tags>
		</move>
		<move>
			<id>0</id>
			<name>1+2+3+4, 1+2</name>
			<command>1+2+3+4, >, +1+2</command>
			<hitLevel>(Special) (TJ), (DES)</hitLevel>
			<damage/>
			<StartUp>Air</StartUp>
			<BlockFrame/>
			<HitFrame/>
			<CounterHitFrame/>
			<tags>
				<NeedsWork/>
			</tags>
		</move>
		<move>
			<id>1</id>
			<name>d/b+1</name>
			<command>d/b+1</command>
			<hitLevel>(Special) (TC)</hitLevel>
			<damage/>
			<StartUp>RC(cs4)</StartUp>
			<BlockFrame/>
			<HitFrame/>
			<CounterHitFrame/>
			<tags>
				<NeedsWork/>
			</tags>
		</move>
		<move>
			<id>0</id>
			<name>d/b+1~1</name>
			<command>d/b+1~1</command>
			<hitLevel>h</hitLevel>
			<damage>31</damage>
			<StartUp>13~14 (26~)</StartUp>
			<BlockFrame>+4~+5</BlockFrame>
			<HitFrame>KND</HitFrame>
			<CounterHitFrame>KND</CounterHitFrame>
			<tags>
				<NeedsWork/>
				<TailSpin/>
			</tags>
		</move>
		<move>
			<id>0</id>
			<name>d/b+1~2</name>
			<command>d/b+1~2</command>
			<hitLevel>h! (Sky)</hitLevel>
			<damage>20(,3)</damage>
			<StartUp>40?~ 3~)</StartUp>
			<BlockFrame>KND</BlockFrame>
			<HitFrame>KND</HitFrame>
			<CounterHitFrame>KND</CounterHitFrame>
			<tags>
				<NeedsWork/>
			</tags>
		</move>
		<move>
			<id>0</id>
			<name>d/b+1~3</name>
			<command>d/b+1~3</command>
			<hitLevel>m (TJ)</hitLevel>
			<damage>30</damage>
			<StartUp>26 Air(39~)</StartUp>
			<BlockFrame>-10?</BlockFrame>
			<HitFrame>KND</HitFrame>
			<CounterHitFrame>KND</CounterHitFrame>
			<tags>
				<NeedsWork/>
			</tags>
		</move>
		<move>
			<id>0</id>
			<name>d/b+1~4</name>
			<command>d/b+1~4</command>
			<hitLevel>m</hitLevel>
			<damage>30</damage>
			<StartUp>20~21a (33~)</StartUp>
			<BlockFrame>-9~-8</BlockFrame>
			<HitFrame>Launch</HitFrame>
			<CounterHitFrame>Launch</CounterHitFrame>
			<tags>
				<NeedsWork/>
			</tags>
		</move>
		<move>
			<id>0</id>
			<name>f+3+4 (to SBT)</name>
			<command>f+3+4 (to SBT)</command>
			<hitLevel>(Special) (TJ)(SBT)</hitLevel>
			<damage/>
			<StartUp>20~21 (33~)</StartUp>
			<BlockFrame/>
			<HitFrame/>
			<CounterHitFrame/>
			<tags>
				<NeedsWork/>
			</tags>
		</move>
		<move>
			<id>0</id>
			<name>f+3+4, b or D</name>
			<command>f+3+4, >, b or D</command>
			<hitLevel>(Special)</hitLevel>
			<damage/>
			<StartUp>RC</StartUp>
			<BlockFrame/>
			<HitFrame/>
			<CounterHitFrame/>
			<tags>
				<NeedsWork/>
			</tags>
		</move>
		<move>
			<id>1</id>
			<name>SBT 1</name>
			<command>SBT 1</command>
			<hitLevel>m</hitLevel>
			<damage>12</damage>
			<StartUp>13(38~)</StartUp>
			<BlockFrame>-15</BlockFrame>
			<HitFrame>0</HitFrame>
			<CounterHitFrame>0</CounterHitFrame>
			<tags>
				<NeedsWork/>
				<Punishable>-15</Punishable>
			</tags>
		</move>
		<move>
			<id>0</id>
			<name>SBT 1, 2</name>
			<command>SBT 1, >, +2</command>
			<hitLevel>m, m</hitLevel>
			<damage>12,13</damage>
			<StartUp>13(38~)</StartUp>
			<BlockFrame>-9</BlockFrame>
			<HitFrame>-4</HitFrame>
			<CounterHitFrame>+1 OC</CounterHitFrame>
			<tags>
				<NeedsWork/>
				<Safe/>
			</tags>
		</move>
		<move>
			<id>1</id>
			<name>SBT 1, 2, 1</name>
			<command>SBT 1, >, +2, >, +1</command>
			<hitLevel>m, m, m</hitLevel>
			<damage>12,13,7</damage>
			<StartUp>13(38~)</StartUp>
			<BlockFrame>-20</BlockFrame>
			<HitFrame>-12</HitFrame>
			<CounterHitFrame>-12</CounterHitFrame>
			<tags>
				<NeedsWork/>
				<Punishable>-20</Punishable>
			</tags>
		</move>
		<move>
			<id>2</id>
			<name>SBT 1, 2, 1 , 3+4</name>
			<command>SBT 1, >, +2, >, +1, >, +3+4</command>
			<hitLevel>m, m, m, mm</hitLevel>
			<damage>12,13,7,5,28</damage>
			<StartUp>13(38~)</StartUp>
			<BlockFrame>-18</BlockFrame>
			<HitFrame>KND</HitFrame>
			<CounterHitFrame>KND</CounterHitFrame>
			<tags>
				<NeedsWork/>
				<Punishable>-18</Punishable>
			</tags>
		</move>
		<move>
			<id>3</id>
			<name>SBT 1, 2, 1 , 3+4, 1+2</name>
			<command>SBT 1, >, +2, >, +1, >, +3+4, >, +1+2</command>
			<hitLevel>m, m, m, mm, (DES)</hitLevel>
			<damage>12,13,7,5,28</damage>
			<StartUp>13(38~)</StartUp>
			<BlockFrame>-18</BlockFrame>
			<HitFrame>KND</HitFrame>
			<CounterHitFrame>KND</CounterHitFrame>
			<tags>
				<NeedsWork/>
				<Punishable>-18</Punishable>
			</tags>
		</move>
		<move>
			<id>4</id>
			<name>SBT 2</name>
			<command>SBT 2</command>
			<hitLevel>m</hitLevel>
			<damage>25</damage>
			<StartUp>16~30 (41~)</StartUp>
			<BlockFrame>-8~+?</BlockFrame>
			<HitFrame>KND</HitFrame>
			<CounterHitFrame>KND</CounterHitFrame>
			<tags>
				<NeedsWork/>
			</tags>
		</move>
		<move>
			<id>0</id>
			<name>SBT 2, 1+2</name>
			<command>SBT 2, >, +1+2</command>
			<hitLevel>m, (DES)</hitLevel>
			<damage>25</damage>
			<StartUp>16~30 (41~)</StartUp>
			<BlockFrame>-~+?</BlockFrame>
			<HitFrame>KND</HitFrame>
			<CounterHitFrame>KND</CounterHitFrame>
			<tags>
				<NeedsWork/>
			</tags>
		</move>
		<move>
			<id>1</id>
			<name>SBT 3</name>
			<command>SBT 3</command>
			<hitLevel>l</hitLevel>
			<damage>17</damage>
			<StartUp>16~18 RC (41~)</StartUp>
			<BlockFrame>-14?~-12?</BlockFrame>
			<HitFrame>+3~+5 OC</HitFrame>
			<CounterHitFrame>KND</CounterHitFrame>
			<tags>
				<NeedsWork/>
			</tags>
		</move>
		<move>
			<id>0</id>
			<name>SBT 4</name>
			<command>SBT 4</command>
			<hitLevel>m</hitLevel>
			<damage>22(,5)</damage>
			<StartUp>18~19( Air) (43~)</StartUp>
			<BlockFrame>-27~-26</BlockFrame>
			<HitFrame>Launch</HitFrame>
			<CounterHitFrame>Launch</CounterHitFrame>
			<tags>
				<NeedsWork/>
			</tags>
		</move>
		<move>
			<id>0</id>
			<name>d+1+2 or From special move (to DES)</name>
			<command>d+1+2 or From special move (to DES)</command>
			<hitLevel>(DES)</hitLevel>
			<damage/>
			<StartUp>18~19() (43~)</StartUp>
			<BlockFrame/>
			<HitFrame/>
			<CounterHitFrame/>
			<tags>
				<NeedsWork/>
			</tags>
		</move>
		<move>
			<id>0</id>
			<name>DES b or F</name>
			<command>DES b or F</command>
			<hitLevel>(DES)</hitLevel>
			<damage/>
			<StartUp>18~19() (43~)</StartUp>
			<BlockFrame/>
			<HitFrame/>
			<CounterHitFrame/>
			<tags>
				<NeedsWork/>
			</tags>
		</move>
		<move>
			<id>0</id>
			<name>DES d+1+2 or D/B (Cancel)</name>
			<command>DES d+1+2 or D/B (Cancel)</command>
			<hitLevel>(DES)</hitLevel>
			<damage/>
			<StartUp>18~19() (43~)</StartUp>
			<BlockFrame/>
			<HitFrame/>
			<CounterHitFrame/>
			<tags>
				<NeedsWork/>
			</tags>
		</move>
		<move>
			<id>0</id>
			<name>DES 1</name>
			<command>DES 1</command>
			<hitLevel>mmhhhm</hitLevel>
			<damage>3*5,20</damage>
			<StartUp>14,,,</StartUp>
			<BlockFrame>-9</BlockFrame>
			<HitFrame>CS</HitFrame>
			<CounterHitFrame>CS</CounterHitFrame>
			<tags>
				<NeedsWork/>
				<Safe/>
			</tags>
		</move>
		<move>
			<id>0</id>
			<name>DES 2</name>
			<command>DES 2</command>
			<hitLevel>mmm</hitLevel>
			<damage>5*3?</damage>
			<StartUp>20,,</StartUp>
			<BlockFrame>-6?</BlockFrame>
			<HitFrame>Launch (JG?)</HitFrame>
			<CounterHitFrame>Launch (JG?)</CounterHitFrame>
			<tags>
				<NeedsWork/>
			</tags>
		</move>
		<move>
			<id>0</id>
			<name>DES 2 When hit 1</name>
			<command>DES 2 When hit 1</command>
			<hitLevel>m x 3, h!</hitLevel>
			<damage>5*3?,</damage>
			<StartUp>20,,</StartUp>
			<BlockFrame/>
			<HitFrame>Launch</HitFrame>
			<CounterHitFrame/>
			<tags>
				<NeedsWork/>
			</tags>
		</move>
		<move>
			<id>0</id>
			<name>DES 3 or 4</name>
			<command>DES 3 or 4</command>
			<hitLevel>(Special)</hitLevel>
			<damage/>
			<StartUp>20,,</StartUp>
			<BlockFrame/>
			<HitFrame/>
			<CounterHitFrame/>
			<tags>
				<NeedsWork/>
			</tags>
		</move>
		<move>
			<id>0</id>
			<name>DES 1+2</name>
			<command>DES 1+2</command>
			<hitLevel>hhh</hitLevel>
			<damage>7,7,20</damage>
			<StartUp>16,,</StartUp>
			<BlockFrame>0</BlockFrame>
			<HitFrame>KND</HitFrame>
			<CounterHitFrame>KND</CounterHitFrame>
			<tags>
				<NeedsWork/>
				<Safe/>
				<Homing/>
				<TailSpin/>
			</tags>
		</move>
		<move>
			<id>0</id>
			<name>DES f+1</name>
			<command>DES f+1</command>
			<hitLevel>h x 7</hitLevel>
			<damage>3*7</damage>
			<StartUp>12,,,</StartUp>
			<BlockFrame>-?</BlockFrame>
			<HitFrame>+?</HitFrame>
			<CounterHitFrame>+?</CounterHitFrame>
			<tags>
				<NeedsWork/>
			</tags>
		</move>
		<move>
			<id>0</id>
			<name>DES f+2</name>
			<command>DES f+2</command>
			<hitLevel>(Sky)!</hitLevel>
			<damage>3,2,2,2?</damage>
			<StartUp>10,,,</StartUp>
			<BlockFrame/>
			<HitFrame>KND</HitFrame>
			<CounterHitFrame>KND</CounterHitFrame>
			<tags>
				<NeedsWork/>
			</tags>
		</move>
		<move>
			<id>0</id>
			<name>DES f+1+2</name>
			<command>DES f+1+2</command>
			<hitLevel>m x 8</hitLevel>
			<damage>3*7,13</damage>
			<StartUp>23,,,</StartUp>
			<BlockFrame>+3</BlockFrame>
			<HitFrame>CS</HitFrame>
			<CounterHitFrame>CS</CounterHitFrame>
			<tags>
				<NeedsWork/>
				<Safe/>
			</tags>
		</move>
		<move>
			<id>0</id>
			<name>DES f+1+2, 1+2</name>
			<command>DES f+1+2, >, +1+2</command>
			<hitLevel>m x 5, m</hitLevel>
			<damage>3*5,20(,3)</damage>
			<StartUp>23,,,( RBT)</StartUp>
			<BlockFrame>-53</BlockFrame>
			<HitFrame>Launch</HitFrame>
			<CounterHitFrame>Launch</CounterHitFrame>
			<tags>
				<NeedsWork/>
				<Punishable>-53</Punishable>
			</tags>
		</move>
		<move>
			<id>1</id>
			<name>DES d+1</name>
			<command>DES d+1</command>
			<hitLevel>l x 5 (TC)</hitLevel>
			<damage>4*4,8</damage>
			<StartUp>20~21,</StartUp>
			<BlockFrame>-12</BlockFrame>
			<HitFrame>-2</HitFrame>
			<CounterHitFrame>-2</CounterHitFrame>
			<tags>
				<NeedsWork/>
				<Punishable>-12</Punishable>
			</tags>
		</move>
		<move>
			<id>0</id>
			<name>DES d+2</name>
			<command>DES d+2</command>
			<hitLevel>llll</hitLevel>
			<damage>5*4</damage>
			<StartUp>30,,,</StartUp>
			<BlockFrame>-14~-13</BlockFrame>
			<HitFrame>+2~+3</HitFrame>
			<CounterHitFrame>2~+3</CounterHitFrame>
			<tags>
				<NeedsWork/>
			</tags>
		</move>
		<move>
			<id>0</id>
			<name>DES d+2, *</name>
			<command>DES d+2, >, *</command>
			<hitLevel>l x 5 or 6</hitLevel>
			<damage>5*5or6</damage>
			<StartUp>30,,,</StartUp>
			<BlockFrame>-14~-13</BlockFrame>
			<HitFrame>+2~+3</HitFrame>
			<CounterHitFrame>2~+3</CounterHitFrame>
			<tags>
				<NeedsWork/>
			</tags>
		</move>
		<move>
			<id>1</id>
			<name>DES b+2</name>
			<command>DES b+2</command>
			<hitLevel>m</hitLevel>
			<damage>17</damage>
			<StartUp>18</StartUp>
			<BlockFrame>-12</BlockFrame>
			<HitFrame>0</HitFrame>
			<CounterHitFrame>CS</CounterHitFrame>
			<tags>
				<NeedsWork/>
				<Punishable>-12</Punishable>
			</tags>
		</move>
		<move>
			<id>0</id>
			<name>DES b+2, 1</name>
			<command>DES b+2, >, +1</command>
			<hitLevel>m, m, Sm x 4</hitLevel>
			<damage>17,8,5*4?</damage>
			<StartUp>18</StartUp>
			<BlockFrame>-8 OC</BlockFrame>
			<HitFrame>KND</HitFrame>
			<CounterHitFrame>KND</CounterHitFrame>
			<tags>
				<NeedsWork/>
			</tags>
		</move>
		<move>
			<id>1</id>
			<name>DES b+3+4 or b, b or u/b, b</name>
			<command>DES b+3+4 or b, >, b or u/b, >, b</command>
			<hitLevel>(Special) (TJ)</hitLevel>
			<damage/>
			<StartUp>Air</StartUp>
			<BlockFrame/>
			<HitFrame/>
			<CounterHitFrame/>
			<tags>
				<NeedsWork/>
			</tags>
		</move>
		<move>
			<id>2</id>
			<name>DES u or d+3+4</name>
			<command>DES u or d+3+4</command>
			<hitLevel>(Special) (TJ)</hitLevel>
			<damage/>
			<StartUp/>
			<BlockFrame/>
			<HitFrame/>
			<CounterHitFrame/>
			<tags>
				<NeedsWork/>
			</tags>
		</move>
		<move>
			<id>0</id>
			<name>DES u or d+3+4, 1</name>
			<command>DES u or d+3+4, >, +1</command>
			<hitLevel>(Special) (TJ), m</hitLevel>
			<damage>25</damage>
			<StartUp>20(44~)</StartUp>
			<BlockFrame>-20</BlockFrame>
			<HitFrame>CS</HitFrame>
			<CounterHitFrame>CS</CounterHitFrame>
			<tags>
				<NeedsWork/>
				<Punishable>-20</Punishable>
			</tags>
		</move>
		<move>
			<id>1</id>
			<name>DES u/b or u or u/f+1+2</name>
			<command>DES u/b or u or u/f+1+2</command>
			<hitLevel>mmm (TJ)</hitLevel>
			<damage>9*3</damage>
			<StartUp>29,,,</StartUp>
			<BlockFrame>-12 OC</BlockFrame>
			<HitFrame>CS</HitFrame>
			<CounterHitFrame>CS</CounterHitFrame>
			<tags>
				<NeedsWork/>
			</tags>
		</move>
		<move>
			<id>0</id>
			<name>DES u/f+1+2, 1+2</name>
			<command>DES u/f+1+2, >, +1+2</command>
			<hitLevel>m x 3 (TJ), (Special)</hitLevel>
			<damage>9*3</damage>
			<StartUp>29,,,</StartUp>
			<BlockFrame>-12 OC</BlockFrame>
			<HitFrame>CS</HitFrame>
			<CounterHitFrame>CS</CounterHitFrame>
			<tags>
				<NeedsWork/>
			</tags>
		</move>
		<move>
			<id>1</id>
			<name>DES BT 1 or 2</name>
			<command>DES BT 1 or 2</command>
			<hitLevel>m x 6</hitLevel>
			<damage>4*6</damage>
			<StartUp>19,,,</StartUp>
			<BlockFrame>-16</BlockFrame>
			<HitFrame>CS</HitFrame>
			<CounterHitFrame>CS</CounterHitFrame>
			<tags>
				<NeedsWork/>
				<Punishable>-16</Punishable>
			</tags>
		</move>
		<move>
			<id>0</id>
			<name>in rage DES b+1+2</name>
			<command>in rage DES b+1+2</command>
			<hitLevel>h x 6</hitLevel>
			<damage/>
			<StartUp>19,,,</StartUp>
			<BlockFrame>+</BlockFrame>
			<HitFrame>KND</HitFrame>
			<CounterHitFrame>KND</CounterHitFrame>
			<tags>
				<NeedsWork/>
				<RageArt/>
			</tags>
		</move>
		<move>
			<id>0</id>
			<name>DES f+3+4 or f, f (to DBT)</name>
			<command>DES f+3+4 or f, >, f (to DBT)</command>
			<hitLevel>(DBT)</hitLevel>
			<damage/>
			<StartUp>19,,,</StartUp>
			<BlockFrame/>
			<HitFrame/>
			<CounterHitFrame/>
			<tags>
				<NeedsWork/>
			</tags>
		</move>
		<move>
			<id>1</id>
			<name>DBT b (Cancel)</name>
			<command>DBT b (Cancel)</command>
			<hitLevel>(Special)</hitLevel>
			<damage/>
			<StartUp>19,,,</StartUp>
			<BlockFrame/>
			<HitFrame/>
			<CounterHitFrame/>
			<tags>
				<NeedsWork/>
			</tags>
		</move>
		<move>
			<id>0</id>
			<name>DBT f+3+4, u or D</name>
			<command>DBT f+3+4, >, u or D</command>
			<hitLevel>(Special) (TJ)</hitLevel>
			<damage/>
			<StartUp>19,,,</StartUp>
			<BlockFrame/>
			<HitFrame/>
			<CounterHitFrame/>
			<tags>
				<NeedsWork/>
			</tags>
		</move>
		<move>
			<id>1</id>
			<name>DBT 1</name>
			<command>DBT 1</command>
			<hitLevel>h x 6</hitLevel>
			<damage>5*6</damage>
			<StartUp>24,,,</StartUp>
			<BlockFrame>+9</BlockFrame>
			<HitFrame>+11</HitFrame>
			<CounterHitFrame>+11</CounterHitFrame>
			<tags>
				<NeedsWork/>
				<Safe/>
			</tags>
		</move>
		<move>
			<id>0</id>
			<name>DBT 2</name>
			<command>DBT 2</command>
			<hitLevel>mmhhh</hitLevel>
			<damage>8,8,8,20,25?</damage>
			<StartUp>16~17,,,</StartUp>
			<BlockFrame>-14</BlockFrame>
			<HitFrame>KND</HitFrame>
			<CounterHitFrame>KND</CounterHitFrame>
			<tags>
				<NeedsWork/>
				<Punishable>-14</Punishable>
			</tags>
		</move>
		<move>
			<id>0</id>
			<name>DBT 2, 1+2</name>
			<command>DBT 2, >, +1+2</command>
			<hitLevel>mmhhh, (Special)</hitLevel>
			<damage>8,8,8,20,25?</damage>
			<StartUp>16~17,,,</StartUp>
			<BlockFrame>-14</BlockFrame>
			<HitFrame>KND</HitFrame>
			<CounterHitFrame>KND</CounterHitFrame>
			<tags>
				<NeedsWork/>
				<Punishable>-14</Punishable>
			</tags>
		</move>
		<move>
			<id>1</id>
			<name>DBT 2, 1</name>
			<command>DBT 2, >, +1</command>
			<hitLevel>mmhh, h (TJ)</hitLevel>
			<damage>8,8,8,20,45?</damage>
			<StartUp>16~17,,,( Air)</StartUp>
			<BlockFrame>-11 OC</BlockFrame>
			<HitFrame>KND</HitFrame>
			<CounterHitFrame>KND</CounterHitFrame>
			<tags>
				<NeedsWork/>
			</tags>
		</move>
		<move>
			<id>1</id>
			<name>DBT 2, 1, 1+2</name>
			<command>DBT 2, >, +1, >, +1+2</command>
			<hitLevel>mmhh, h (TJ), (Special)</hitLevel>
			<damage>8,8,8,20,45?</damage>
			<StartUp>16~17,,,()( Air)</StartUp>
			<BlockFrame>-11 OC</BlockFrame>
			<HitFrame>KND</HitFrame>
			<CounterHitFrame>KND</CounterHitFrame>
			<tags>
				<NeedsWork/>
			</tags>
		</move>
		<move>
			<id>2</id>
			<name>DBT 1+2</name>
			<command>DBT 1+2</command>
			<hitLevel>mmmm</hitLevel>
			<damage>5,5,5,20?</damage>
			<StartUp>12,,,</StartUp>
			<BlockFrame>-5</BlockFrame>
			<HitFrame>KND</HitFrame>
			<CounterHitFrame>KND</CounterHitFrame>
			<tags>
				<NeedsWork/>
				<Safe/>
			</tags>
		</move>
		<move>
			<id>0</id>
			<name>Command</name>
			<command>Command</command>
			<hitLevel>Hit level</hitLevel>
			<damage>Damage</damage>
			<StartUp>Start up frame</StartUp>
			<BlockFrame>Block frame</BlockFrame>
			<HitFrame>Hit frame</HitFrame>
			<CounterHitFrame>Counter hit frame</CounterHitFrame>
			<tags>
				<NeedsWork/>
				<Notes/>
			</tags>
		</move>
		<move>
			<id>0</id>
			<name>1</name>
			<command>+1</command>
			<hitLevel>h</hitLevel>
			<damage>7</damage>
			<StartUp>10</StartUp>
			<BlockFrame>+1</BlockFrame>
			<HitFrame>+8</HitFrame>
			<CounterHitFrame>+8</CounterHitFrame>
			<tags>
				<NeedsWork/>
				<Safe/>
			</tags>
		</move>
		<move>
			<id>0</id>
			<name>2</name>
			<command>+2</command>
			<hitLevel>h</hitLevel>
			<damage>10</damage>
			<StartUp>12</StartUp>
			<BlockFrame>-6</BlockFrame>
			<HitFrame>+5</HitFrame>
			<CounterHitFrame>+5</CounterHitFrame>
			<tags>
				<NeedsWork/>
				<Safe/>
			</tags>
		</move>
		<move>
			<id>0</id>
			<name>3</name>
			<command>+3</command>
			<hitLevel>m</hitLevel>
			<damage>12</damage>
			<StartUp>14~15</StartUp>
			<BlockFrame>-12~-11</BlockFrame>
			<HitFrame>-1~0</HitFrame>
			<CounterHitFrame>-1~0</CounterHitFrame>
			<tags>
				<NeedsWork/>
			</tags>
		</move>
		<move>
			<id>0</id>
			<name>4</name>
			<command>+4</command>
			<hitLevel>h</hitLevel>
			<damage>24</damage>
			<StartUp>13</StartUp>
			<BlockFrame>-5</BlockFrame>
			<HitFrame>KND</HitFrame>
			<CounterHitFrame>KND</CounterHitFrame>
			<tags>
				<NeedsWork/>
				<Safe/>
				<TailSpin/>
				<Homing/>
			</tags>
		</move>
		<move>
			<id>0</id>
			<name>b+1</name>
			<command>b+1</command>
			<hitLevel>m</hitLevel>
			<damage>15</damage>
			<StartUp>15~16 RC</StartUp>
			<BlockFrame>-5~-4</BlockFrame>
			<HitFrame>+8~+9</HitFrame>
			<CounterHitFrame>+8~+9</CounterHitFrame>
			<tags>
				<NeedsWork/>
			</tags>
		</move>
		<move>
			<id>0</id>
			<name>b+2</name>
			<command>b+2</command>
			<hitLevel>m</hitLevel>
			<damage>12</damage>
			<StartUp>18</StartUp>
			<BlockFrame>-12</BlockFrame>
			<HitFrame>-2</HitFrame>
			<CounterHitFrame>-2</CounterHitFrame>
			<tags>
				<NeedsWork/>
				<Punishable>-12</Punishable>
			</tags>
		</move>
		<move>
			<id>0</id>
			<name>b+3</name>
			<command>b+3</command>
			<hitLevel>m</hitLevel>
			<damage>26</damage>
			<StartUp>20~21</StartUp>
			<BlockFrame>-8~-7</BlockFrame>
			<HitFrame>KND</HitFrame>
			<CounterHitFrame>KND</CounterHitFrame>
			<tags>
				<NeedsWork/>
				<Homing/>
			</tags>
		</move>
		<move>
			<id>0</id>
			<name>b+4</name>
			<command>b+4</command>
			<hitLevel>m (TJ)</hitLevel>
			<damage>17</damage>
			<StartUp>15~16</StartUp>
			<BlockFrame>-12~-11</BlockFrame>
			<HitFrame>-3~-2</HitFrame>
			<CounterHitFrame>CS</CounterHitFrame>
			<tags>
				<NeedsWork/>
			</tags>
		</move>
		<move>
			<id>0</id>
			<name>f+1</name>
			<command>f+1</command>
			<hitLevel>h</hitLevel>
			<damage>7</damage>
			<StartUp>10</StartUp>
			<BlockFrame>+1</BlockFrame>
			<HitFrame>+8</HitFrame>
			<CounterHitFrame>+8</CounterHitFrame>
			<tags>
				<NeedsWork/>
				<Safe/>
			</tags>
		</move>
		<move>
			<id>0</id>
			<name>f+2</name>
			<command>f+2</command>
			<hitLevel>m</hitLevel>
			<damage>12</damage>
			<StartUp>17</StartUp>
			<BlockFrame>-4</BlockFrame>
			<HitFrame>+7</HitFrame>
			<CounterHitFrame>+7</CounterHitFrame>
			<tags>
				<NeedsWork/>
				<Safe/>
			</tags>
		</move>
		<move>
			<id>0</id>
			<name>f+3</name>
			<command>f+3</command>
			<hitLevel>h</hitLevel>
			<damage>13</damage>
			<StartUp>14~15</StartUp>
			<BlockFrame>-14~-13</BlockFrame>
			<HitFrame>-3~-2</HitFrame>
			<CounterHitFrame>-3~-2</CounterHitFrame>
			<tags>
				<NeedsWork/>
			</tags>
		</move>
		<move>
			<id>0</id>
			<name>f+4</name>
			<command>f+4</command>
			<hitLevel>m</hitLevel>
			<damage>14</damage>
			<StartUp>16</StartUp>
			<BlockFrame>-12</BlockFrame>
			<HitFrame>-2</HitFrame>
			<CounterHitFrame>-2</CounterHitFrame>
			<tags>
				<NeedsWork/>
				<Punishable>-12</Punishable>
				<Homing/>
			</tags>
		</move>
		<move>
			<id>0</id>
			<name>f, F+1</name>
			<command>f, >, F+1</command>
			<hitLevel>h</hitLevel>
			<damage>7</damage>
			<StartUp>10(11~)</StartUp>
			<BlockFrame>+1</BlockFrame>
			<HitFrame>+8</HitFrame>
			<CounterHitFrame>+8</CounterHitFrame>
			<tags>
				<NeedsWork/>
				<Safe/>
			</tags>
		</move>
		<move>
			<id>1</id>
			<name>f, F+2</name>
			<command>f, >, F+2</command>
			<hitLevel>m (TJ)</hitLevel>
			<damage>18</damage>
			<StartUp>16~17 (17~)</StartUp>
			<BlockFrame>-18~-17</BlockFrame>
			<HitFrame>KND</HitFrame>
			<CounterHitFrame>KND</CounterHitFrame>
			<tags>
				<NeedsWork/>
			</tags>
		</move>
		<move>
			<id>1</id>
			<name>f, F+3</name>
			<command>f, >, F+3</command>
			<hitLevel>m</hitLevel>
			<damage>12</damage>
			<StartUp>18~19 (19~)</StartUp>
			<BlockFrame>-18~-17</BlockFrame>
			<HitFrame>-6~-5</HitFrame>
			<CounterHitFrame>-6~-5</CounterHitFrame>
			<tags>
				<NeedsWork/>
			</tags>
		</move>
		<move>
			<id>1</id>
			<name>f, F+4</name>
			<command>f, >, F+4</command>
			<hitLevel>m</hitLevel>
			<damage>18</damage>
			<StartUp>19~22 (20~)</StartUp>
			<BlockFrame>-11~-8</BlockFrame>
			<HitFrame>Throw(+5OB)</HitFrame>
			<CounterHitFrame>Throw(+5OB)</CounterHitFrame>
			<tags>
				<NeedsWork/>
			</tags>
		</move>
		<move>
			<id>1</id>
			<name>d+1</name>
			<command>d+1</command>
			<hitLevel>Sm (TC)</hitLevel>
			<damage>5</damage>
			<StartUp>10 RC(cs4)</StartUp>
			<BlockFrame>-5</BlockFrame>
			<HitFrame>+6</HitFrame>
			<CounterHitFrame>+6</CounterHitFrame>
			<tags>
				<NeedsWork/>
				<Safe/>
			</tags>
		</move>
		<move>
			<id>0</id>
			<name>d+2</name>
			<command>d+2</command>
			<hitLevel>m</hitLevel>
			<damage>17</damage>
			<StartUp>24~25</StartUp>
			<BlockFrame>-14~-13</BlockFrame>
			<HitFrame>+2~+3 OC</HitFrame>
			<CounterHitFrame>+2~+3 OC</CounterHitFrame>
			<tags>
				<NeedsWork/>
			</tags>
		</move>
		<move>
			<id>0</id>
			<name>d+3</name>
			<command>d+3</command>
			<hitLevel>l (TJ), (Special) (TC)</hitLevel>
			<damage>17</damage>
			<StartUp>23?s~</StartUp>
			<BlockFrame>-19?s~</BlockFrame>
			<HitFrame>+9~+13?</HitFrame>
			<CounterHitFrame>KND</CounterHitFrame>
			<tags>
				<NeedsWork/>
			</tags>
		</move>
		<move>
			<id>0</id>
			<name>d+4</name>
			<command>d+4</command>
			<hitLevel>l</hitLevel>
			<damage>15</damage>
			<StartUp>17</StartUp>
			<BlockFrame>-16</BlockFrame>
			<HitFrame>-5</HitFrame>
			<CounterHitFrame>-5</CounterHitFrame>
			<tags>
				<NeedsWork/>
				<Punishable>-16</Punishable>
			</tags>
		</move>
		<move>
			<id>0</id>
			<name>d/b+1</name>
			<command>d/b+1</command>
			<hitLevel>(Special) (TC)</hitLevel>
			<damage/>
			<StartUp>RC(cs4)</StartUp>
			<BlockFrame/>
			<HitFrame/>
			<CounterHitFrame/>
			<tags>
				<NeedsWork/>
			</tags>
		</move>
		<move>
			<id>0</id>
			<name>d/b+2</name>
			<command>d/b+2</command>
			<hitLevel>m</hitLevel>
			<damage>17</damage>
			<StartUp>18</StartUp>
			<BlockFrame>-18</BlockFrame>
			<HitFrame>-5</HitFrame>
			<CounterHitFrame>-5</CounterHitFrame>
			<tags>
				<NeedsWork/>
				<Punishable>-18</Punishable>
			</tags>
		</move>
		<move>
			<id>0</id>
			<name>d/b+3</name>
			<command>d/b+3</command>
			<hitLevel>l (TC)</hitLevel>
			<damage>11</damage>
			<StartUp>16 RC(cs4)</StartUp>
			<BlockFrame>-12?</BlockFrame>
			<HitFrame>-2?</HitFrame>
			<CounterHitFrame>+5</CounterHitFrame>
			<tags>
				<NeedsWork/>
			</tags>
		</move>
		<move>
			<id>0</id>
			<name>d/b+4</name>
			<command>d/b+4</command>
			<hitLevel>l (TC)</hitLevel>
			<damage>23</damage>
			<StartUp>23~24 (cs6)</StartUp>
			<BlockFrame>-18~-17</BlockFrame>
			<HitFrame>KND</HitFrame>
			<CounterHitFrame>KND</CounterHitFrame>
			<tags>
				<NeedsWork/>
			</tags>
		</move>
		<move>
			<id>0</id>
			<name>FC+1</name>
			<command>FC+1</command>
			<hitLevel>Sm (TC)</hitLevel>
			<damage>5</damage>
			<StartUp>10 RC</StartUp>
			<BlockFrame>-5</BlockFrame>
			<HitFrame>+6</HitFrame>
			<CounterHitFrame>+6</CounterHitFrame>
			<tags>
				<NeedsWork/>
				<Safe/>
			</tags>
		</move>
		<move>
			<id>0</id>
			<name>FC+2</name>
			<command>FC+2</command>
			<hitLevel>Sm (TC)</hitLevel>
			<damage>8</damage>
			<StartUp>11 RC</StartUp>
			<BlockFrame>-4</BlockFrame>
			<HitFrame>+7</HitFrame>
			<CounterHitFrame>+7</CounterHitFrame>
			<tags>
				<NeedsWork/>
				<Safe/>
			</tags>
		</move>
		<move>
			<id>0</id>
			<name>FC+3</name>
			<command>FC+3</command>
			<hitLevel>l (TC)</hitLevel>
			<damage>12</damage>
			<StartUp>16 RC</StartUp>
			<BlockFrame>-17</BlockFrame>
			<HitFrame>-3</HitFrame>
			<CounterHitFrame>-3</CounterHitFrame>
			<tags>
				<NeedsWork/>
				<Punishable>-17</Punishable>
			</tags>
		</move>
		<move>
			<id>0</id>
			<name>FC+4</name>
			<command>FC+4</command>
			<hitLevel>l (TC)</hitLevel>
			<damage>10</damage>
			<StartUp>12 RC</StartUp>
			<BlockFrame>-15</BlockFrame>
			<HitFrame>-4</HitFrame>
			<CounterHitFrame>-4</CounterHitFrame>
			<tags>
				<NeedsWork/>
				<Punishable>-15</Punishable>
			</tags>
		</move>
		<move>
			<id>0</id>
			<name>WS+1</name>
			<command>WS+1</command>
			<hitLevel>m</hitLevel>
			<damage>12</damage>
			<StartUp>13?</StartUp>
			<BlockFrame>-12</BlockFrame>
			<HitFrame>-1</HitFrame>
			<CounterHitFrame>-1</CounterHitFrame>
			<tags>
				<NeedsWork/>
				<Punishable>-12</Punishable>
			</tags>
		</move>
		<move>
			<id>0</id>
			<name>WS+2</name>
			<command>WS+2</command>
			<hitLevel>m</hitLevel>
			<damage>24</damage>
			<StartUp>17~18</StartUp>
			<BlockFrame>-13~-12</BlockFrame>
			<HitFrame>Launch</HitFrame>
			<CounterHitFrame>Launch</CounterHitFrame>
			<tags>
				<NeedsWork/>
			</tags>
		</move>
		<move>
			<id>0</id>
			<name>WS+3</name>
			<command>WS+3</command>
			<hitLevel>m, (Special)</hitLevel>
			<damage>18</damage>
			<StartUp>19 Air</StartUp>
			<BlockFrame>-137</BlockFrame>
			<HitFrame>-124</HitFrame>
			<CounterHitFrame>-124</CounterHitFrame>
			<tags>
				<NeedsWork/>
				<Punishable>-137</Punishable>
			</tags>
		</move>
		<move>
			<id>0</id>
			<name>WS+4</name>
			<command>WS+4</command>
			<hitLevel>m</hitLevel>
			<damage>15</damage>
			<StartUp>11</StartUp>
			<BlockFrame>-5</BlockFrame>
			<HitFrame>+6</HitFrame>
			<CounterHitFrame>+6</CounterHitFrame>
			<tags>
				<NeedsWork/>
				<Safe/>
			</tags>
		</move>
		<move>
			<id>0</id>
			<name>d/f+1</name>
			<command>d/f+1</command>
			<hitLevel>m</hitLevel>
			<damage>10</damage>
			<StartUp>13</StartUp>
			<BlockFrame>-6?</BlockFrame>
			<HitFrame>+5?</HitFrame>
			<CounterHitFrame>+8?</CounterHitFrame>
			<tags>
				<NeedsWork/>
			</tags>
		</move>
		<move>
			<id>0</id>
			<name>d/f+2</name>
			<command>d/f+2</command>
			<hitLevel>m</hitLevel>
			<damage>16</damage>
			<StartUp>16~17</StartUp>
			<BlockFrame>-9~-8</BlockFrame>
			<HitFrame>Launch (JG?)(+7)</HitFrame>
			<CounterHitFrame>Launch (JG?)</CounterHitFrame>
			<tags>
				<NeedsWork/>
			</tags>
		</move>
		<move>
			<id>0</id>
			<name>d/f+3</name>
			<command>d/f+3</command>
			<hitLevel>m</hitLevel>
			<damage>14</damage>
			<StartUp>16</StartUp>
			<BlockFrame>-12</BlockFrame>
			<HitFrame>-1</HitFrame>
			<CounterHitFrame>-1</CounterHitFrame>
			<tags>
				<NeedsWork/>
				<Punishable>-12</Punishable>
			</tags>
		</move>
		<move>
			<id>0</id>
			<name>d/f+4</name>
			<command>d/f+4</command>
			<hitLevel>m</hitLevel>
			<damage>13</damage>
			<StartUp>12</StartUp>
			<BlockFrame>-7</BlockFrame>
			<HitFrame>+4</HitFrame>
			<CounterHitFrame>+4</CounterHitFrame>
			<tags>
				<NeedsWork/>
				<Safe/>
			</tags>
		</move>
		<move>
			<id>0</id>
			<name>u/b or u or u/f+1</name>
			<command>u/b or u or u/f+1</command>
			<hitLevel>m (TJ)</hitLevel>
			<damage>12</damage>
			<StartUp>18</StartUp>
			<BlockFrame>-8</BlockFrame>
			<HitFrame>+3</HitFrame>
			<CounterHitFrame>+3</CounterHitFrame>
			<tags>
				<NeedsWork/>
				<Safe/>
			</tags>
		</move>
		<move>
			<id>0</id>
			<name>u/b or u or u/f+2</name>
			<command>u/b or u or u/f+2</command>
			<hitLevel>h</hitLevel>
			<damage>17</damage>
			<StartUp>15~16</StartUp>
			<BlockFrame>-12~-11</BlockFrame>
			<HitFrame>+9~+10 GB</HitFrame>
			<CounterHitFrame>+9~+10 GB</CounterHitFrame>
			<tags>
				<NeedsWork/>
			</tags>
		</move>
		<move>
			<id>0</id>
			<name>u/b or u or u/f+3</name>
			<command>u/b or u or u/f+3</command>
			<hitLevel>m (TJ)</hitLevel>
			<damage>15</damage>
			<StartUp>20( Air)</StartUp>
			<BlockFrame>-55</BlockFrame>
			<HitFrame>-29(SH)</HitFrame>
			<CounterHitFrame>-29(SH)</CounterHitFrame>
			<tags>
				<NeedsWork/>
				<Punishable>-55</Punishable>
			</tags>
		</move>
		<move>
			<id>0</id>
			<name>u/b+4</name>
			<command>u/b+4</command>
			<hitLevel>m (TJ)</hitLevel>
			<damage>10</damage>
			<StartUp>17~18</StartUp>
			<BlockFrame>-9~-8</BlockFrame>
			<HitFrame>+7~+8</HitFrame>
			<CounterHitFrame>+7~+8</CounterHitFrame>
			<tags>
				<NeedsWork/>
			</tags>
		</move>
		<move>
			<id>0</id>
			<name>u or u/f+4</name>
			<command>u or u/f+4</command>
			<hitLevel>m (TJ)</hitLevel>
			<damage>10</damage>
			<StartUp>15~16</StartUp>
			<BlockFrame>-15~-14?</BlockFrame>
			<HitFrame>+</HitFrame>
			<CounterHitFrame>+</CounterHitFrame>
			<tags>
				<NeedsWork/>
			</tags>
		</move>
		<move>
			<id>0</id>
			<name>SS+1</name>
			<command>SS+1</command>
			<hitLevel>h</hitLevel>
			<damage>7</damage>
			<StartUp>10(11~)</StartUp>
			<BlockFrame>+1</BlockFrame>
			<HitFrame>+8</HitFrame>
			<CounterHitFrame>+8</CounterHitFrame>
			<tags>
				<NeedsWork/>
				<Safe/>
			</tags>
		</move>
		<move>
			<id>0</id>
			<name>SS+2</name>
			<command>SS+2</command>
			<hitLevel>h</hitLevel>
			<damage>10</damage>
			<StartUp>12(13~)</StartUp>
			<BlockFrame>-6</BlockFrame>
			<HitFrame>+5</HitFrame>
			<CounterHitFrame>+5</CounterHitFrame>
			<tags>
				<NeedsWork/>
				<Safe/>
			</tags>
		</move>
		<move>
			<id>0</id>
			<name>SS+3</name>
			<command>SS+3</command>
			<hitLevel>m</hitLevel>
			<damage>12</damage>
			<StartUp>14~15 (15~)</StartUp>
			<BlockFrame>-12~-11</BlockFrame>
			<HitFrame>-1~0</HitFrame>
			<CounterHitFrame>-1~0</CounterHitFrame>
			<tags>
				<NeedsWork/>
			</tags>
		</move>
		<move>
			<id>0</id>
			<name>SS+4</name>
			<command>SS+4</command>
			<hitLevel>l</hitLevel>
			<damage>15</damage>
			<StartUp>24(33~)</StartUp>
			<BlockFrame>-12</BlockFrame>
			<HitFrame>-1</HitFrame>
			<CounterHitFrame>+7</CounterHitFrame>
			<tags>
				<NeedsWork/>
				<Punishable>-12</Punishable>
			</tags>
		</move>
		<move>
			<id>0</id>
			<name>BT 1 or 2</name>
			<command>BT 1 or 2</command>
			<hitLevel>h</hitLevel>
			<damage>15</damage>
			<StartUp>8</StartUp>
			<BlockFrame>-8</BlockFrame>
			<HitFrame>+3</HitFrame>
			<CounterHitFrame>+3</CounterHitFrame>
			<tags>
				<NeedsWork/>
				<Safe/>
			</tags>
		</move>
		<move>
			<id>0</id>
			<name>BT 3</name>
			<command>BT 3</command>
			<hitLevel>h</hitLevel>
			<damage>25</damage>
			<StartUp>10</StartUp>
			<BlockFrame>-8</BlockFrame>
			<HitFrame>KND</HitFrame>
			<CounterHitFrame>KND</CounterHitFrame>
			<tags>
				<NeedsWork/>
				<Safe/>
			</tags>
		</move>
		<move>
			<id>0</id>
			<name>BT 4</name>
			<command>BT 4</command>
			<hitLevel>m (TJ)</hitLevel>
			<damage>20</damage>
			<StartUp>16~17 RBT</StartUp>
			<BlockFrame>-3~-2</BlockFrame>
			<HitFrame>KND</HitFrame>
			<CounterHitFrame>KND</CounterHitFrame>
			<tags>
				<NeedsWork/>
			</tags>
		</move>
	</moves>
</character>
